Workbook

Sheet 96
B2: SEMANA 96 CALANDRA
B3: Lunes 5 ENERO al sábado 10 de ENERO del 2026
B4: INGRESA | E4: =+E71 -> 444.5
B5: EGRESOS | F5: =SUM(E8:E47) -> -1140.0859
B6: DIFERENCIA | E6: =+E4+F5 -> -695.58585 | H6: =+E6/E4 -> -1.5648726
A7: ID | B7: EGRESOS | C7: CANTIDAD | D7: VALOR
A8: =IF('[1]PRODUCTO NACIONAL'!A14<>"",'[1]PRODUCTO NACIONAL'!A14,"") -> M11 | B8: =VLOOKUP(A8,'[1]PRODUCTO NACIONAL'!$A$4:$R$161,6,FALSE) -> IMPRESIÓN SIN DISEÑO, ANCHO 1.8X90gsm | C8: =IFERROR(HLOOKUP(A8,[2]dimensiones_pdfs!$C$3:$Z$5,3,FALSE),0) -> 40.49617 | D8: =VLOOKUP(A8,'[1]PRODUCTO NACIONAL'!$A$4:$R$161,18,FALSE) -> 1.3879841 | E8: =-(+C8*D8) -> -56.208039
A9: =IF('[1]PRODUCTO NACIONAL'!A18<>"",'[1]PRODUCTO NACIONAL'!A18,"") -> M15 | B9: =VLOOKUP(A9,'[1]PRODUCTO NACIONAL'!$A$4:$R$161,6,FALSE) -> D2006 Rollo Panal 1.70m x 160gr | C9: =IFERROR(HLOOKUP(A9,[2]dimensiones_pdfs!$C$3:$Z$5,3,FALSE),0) -> 8.2187219 | D9: =VLOOKUP(A9,'[1]PRODUCTO NACIONAL'!$A$4:$R$161,18,FALSE) -> 1.6348774 | E9: =-(+C9*D9) -> -13.436603
A10: =IF('[1]PRODUCTO NACIONAL'!A27<>"",'[1]PRODUCTO NACIONAL'!A27,"") -> M24 | B10: =IF('[1]PRODUCTO NACIONAL'!F27<>"",'[1]PRODUCTO NACIONAL'!F27,"") -> POLIN GUTMAN T8-10 | T10-12 | C10: =F71 -> 15 | D10: =IF('[1]PRODUCTO NACIONAL'!R27<>"",'[1]PRODUCTO NACIONAL'!R27,"") -> 1.925065 | E10: =-(+C10*D10) -> -28.875975
B11: =+G70 -> BORDADO | C11: =G71 -> 0 | D11: 1 | E11: =-(+C11*D11) -> 0
B12: =+H70 -> DTF/TPU | C12: =H71 -> 0 | D12: 1 | E12: =-(+C12*D12) -> 0
B13: =+I70 -> GORRAS | C13: =I71 -> 0 | D13: 2 | E13: =-(+C13*D13) -> 0
B14: =+J70 -> JARRO | C14: =J71 -> 0 | E14: =-(+C14*D14) -> 0
A15: =IF('[1]PRODUCTO NACIONAL'!A67<>"",'[1]PRODUCTO NACIONAL'!A67,"") -> M64 | B15: =IF('[1]PRODUCTO NACIONAL'!F67<>"",'[1]PRODUCTO NACIONAL'!F67,"") -> CUELLOS20 PEI|NEGRO AZABACHE Y MAS. | C15: =K71 -> 9 | D15: =VLOOKUP(A15,'[1]PRODUCTO NACIONAL'!$A$4:$R$161,18,FALSE) -> 0.47644606 | E15: =-(+C15*D15) -> -4.2880145
A16: =IF('[1]PRODUCTO NACIONAL'!A68<>"",'[1]PRODUCTO NACIONAL'!A68,"") -> M65 | B16: =IF('[1]PRODUCTO NACIONAL'!F68<>"",'[1]PRODUCTO NACIONAL'!F68,"") -> PUÑOS20 PEI|NEGRO AZABACHE Y MAS. | C16: =L71 -> 9 | D16: =VLOOKUP(A16,'[1]PRODUCTO NACIONAL'!$A$4:$R$161,18,FALSE) -> 0.23822303 | E16: =-(+C16*D16) -> -2.1440073
B17: =+M70 -> ENVIOS | C17: =M71 -> 3 | D17: 1 | E17: =-(+C17*D17) -> -3
A18: =IF('[1]PRODUCTO NACIONAL'!A76<>"",'[1]PRODUCTO NACIONAL'!A76,"") -> M73 | B18: =IF('[1]PRODUCTO NACIONAL'!F76<>"",'[1]PRODUCTO NACIONAL'!F76,"") -> CINTA REFLECTIVA DE 3cm de anchox1m | C18: =N71 -> 0 | D18: =VLOOKUP(A18,'[1]PRODUCTO NACIONAL'!$A$4:$R$161,18,FALSE) -> 1.3999945 | E18: =-(+C18*D18) -> 0
A19: =IF('[1]PRODUCTO NACIONAL'!A28<>"",'[1]PRODUCTO NACIONAL'!A28,"") -> M25 | B19: =VLOOKUP(A19,'[1]PRODUCTO NACIONAL'!$A$4:$R$161,6,FALSE) -> ALGODÓN ARUBA PEI AZUL MARINO| COLORES| BLANCO | C19: =IFERROR(HLOOKUP(A19,[2]dimensiones_pdfs!$C$3:$Z$5,3,FALSE),0) -> 0 | D19: =VLOOKUP(A19,'[1]PRODUCTO NACIONAL'!$A$4:$R$161,18,FALSE) -> 4.8341953 | E19: =-(+C19*D19) -> 0
A20: M61 | B20: =VLOOKUP(A20,'[1]PRODUCTO NACIONAL'!$A$4:$R$161,6,FALSE) -> INTERLOCK 40 SPUN 1.2 BLANCO FROZEN | C20: =IFERROR(HLOOKUP(A20,[2]dimensiones_pdfs!$C$3:$Z$5,3,FALSE),0) -> 0 | D20: =VLOOKUP(A20,'[1]PRODUCTO NACIONAL'!$A$4:$R$161,18,FALSE) -> 4.2071437 | E20: =-(+C20*D20) -> 0
A21: =IF('[1]PRODUCTO NACIONAL'!A61<>"",'[1]PRODUCTO NACIONAL'!A61,"") -> M58 | B21: =VLOOKUP(A21,'[1]PRODUCTO NACIONAL'!$A$4:$R$161,6,FALSE) -> PIKE LACOAST 20 PEI CELESTE| CLARO | C21: =IFERROR(HLOOKUP(A21,[2]dimensiones_pdfs!$C$3:$Z$5,3,FALSE),0) -> 0 | D21: =VLOOKUP(A21,'[1]PRODUCTO NACIONAL'!$A$4:$R$161,18,FALSE) -> 4.9712 | E21: =-(+C21*D21) -> 0
A22: =IF('[1]PRODUCTO NACIONAL'!A62<>"",'[1]PRODUCTO NACIONAL'!A62,"") -> M59 | B22: =VLOOKUP(A22,'[1]PRODUCTO NACIONAL'!$A$4:$R$161,6,FALSE) -> PIKE LACOAST 20 PEI AZUL MARINO| OSCURO | C22: =IFERROR(HLOOKUP(A22,[2]dimensiones_pdfs!$C$3:$Z$5,3,FALSE),0) -> 0 | D22: =VLOOKUP(A22,'[1]PRODUCTO NACIONAL'!$A$4:$R$161,18,FALSE) -> 5.56184 | E22: =-(+C22*D22) -> 0
A23: =IF('[1]PRODUCTO NACIONAL'!A21<>"",'[1]PRODUCTO NACIONAL'!A21,"") -> M18 | B23: =VLOOKUP(A23,'[1]PRODUCTO NACIONAL'!$A$4:$R$161,6,FALSE) -> RIBB 150TEX COLORES| POLIESTER | C23: =IFERROR(HLOOKUP(A23,[2]dimensiones_pdfs!$C$3:$Z$5,3,FALSE),0) -> 0 | D23: =VLOOKUP(A23,'[1]PRODUCTO NACIONAL'!$A$4:$R$161,18,FALSE) -> 2.1063822 | E23: =-(+C23*D23) -> 0
A24: =IF('[1]PRODUCTO NACIONAL'!A78<>"",'[1]PRODUCTO NACIONAL'!A78,"") -> M75 | B24: =VLOOKUP(A24,'[1]PRODUCTO NACIONAL'!$A$4:$R$161,6,FALSE) -> Ribb Lugano 100% POLIESTER | C24: =IFERROR(HLOOKUP(A24,[2]dimensiones_pdfs!$C$3:$Z$5,3,FALSE),0) -> 0 | D24: =VLOOKUP(A24,'[1]PRODUCTO NACIONAL'!$A$4:$R$161,18,FALSE) -> 4.5378 | E24: =-(+C24*D24) -> 0
A25: =IF('[1]PRODUCTO NACIONAL'!A30<>"",'[1]PRODUCTO NACIONAL'!A30,"") -> M27 | B25: =VLOOKUP(A25,'[1]PRODUCTO NACIONAL'!$A$4:$R$161,6,FALSE) -> VIOTO PESADA BLANCA|NEGRO|NARANJA FOSFORESCENTE | C25: =IFERROR(HLOOKUP(A25,[2]dimensiones_pdfs!$C$3:$Z$5,3,FALSE),0) -> 0 | D25: =VLOOKUP(A25,'[1]PRODUCTO NACIONAL'!$A$4:$R$161,18,FALSE) -> 1.9499895 | E25: =-(+C25*D25) -> 0
A26: =IF('[1]PRODUCTO NACIONAL'!A22<>"",'[1]PRODUCTO NACIONAL'!A22,"") -> M19 | B26: =VLOOKUP(A26,'[1]PRODUCTO NACIONAL'!$A$4:$R$161,6,FALSE) -> RIVER TEX NEGRO|COLORES | C26: =IFERROR(HLOOKUP(A26,[2]dimensiones_pdfs!$C$3:$Z$5,3,FALSE),0) -> 0 | D26: =VLOOKUP(A26,'[1]PRODUCTO NACIONAL'!$A$4:$R$161,18,FALSE) -> 2.4101474 | E26: =-(+C26*D26) -> 0
A27: =IF('[1]PRODUCTO NACIONAL'!A15<>"",'[1]PRODUCTO NACIONAL'!A15,"") -> M12 | B27: =VLOOKUP(A27,'[1]PRODUCTO NACIONAL'!$A$4:$R$161,6,FALSE) -> LINO JARUBA | C27: =IFERROR(HLOOKUP(A27,[2]dimensiones_pdfs!$C$3:$Z$5,3,FALSE),0) -> 0 | D27: =VLOOKUP(A27,'[1]PRODUCTO NACIONAL'!$A$4:$R$161,18,FALSE) -> 1.8905 | E27: =-(+C27*D27) -> 0
A28: =+'[1]PRODUCTO NACIONAL'!$A$4 -> M1 | B28: =VLOOKUP(A28,'[1]PRODUCTO NACIONAL'!$A$4:$R$161,6,FALSE) -> NYLON | C28: =IFERROR(HLOOKUP(A28,[2]dimensiones_pdfs!$C$3:$Z$5,3,FALSE),0) -> 0 | D28: =VLOOKUP(A28,'[1]PRODUCTO NACIONAL'!$A$4:$R$161,18,FALSE) -> 1.78999 | E28: =-(+C28*D28) -> 0
A29: M17 | B29: =VLOOKUP(A29,'[1]PRODUCTO NACIONAL'!$A$4:$R$161,6,FALSE) -> D2008 Rollo Jersy Spandex 1.80m x 275gr | C29: =IFERROR(HLOOKUP(A29,[2]dimensiones_pdfs!$C$3:$Z$5,3,FALSE),0) -> 0 | D29: =VLOOKUP(A29,'[1]PRODUCTO NACIONAL'!$A$4:$R$161,18,FALSE) -> 3.4782609 | E29: =-(+C29*D29) -> 0
A30: M35 | B30: =VLOOKUP(A30,'[1]PRODUCTO NACIONAL'!$A$4:$R$161,6,FALSE) -> NICO SPORT|BLANCO | C30: =IFERROR(HLOOKUP(A30,[2]dimensiones_pdfs!$C$3:$Z$5,3,FALSE),0) -> 0 | D30: =VLOOKUP(A30,'[1]PRODUCTO NACIONAL'!$A$4:$R$161,18,FALSE) -> 2.316 | E30: =-(+C30*D30) -> 0
A31: M37 | B31: =VLOOKUP(A31,'[1]PRODUCTO NACIONAL'!$A$4:$R$161,6,FALSE) -> MURRAY|BLANCA | C31: =IFERROR(HLOOKUP(A31,[2]dimensiones_pdfs!$C$3:$Z$5,3,FALSE),0) -> 0 | D31: =VLOOKUP(A31,'[1]PRODUCTO NACIONAL'!$A$4:$R$161,18,FALSE) -> 2.2825013 | E31: =-(+C31*D31) -> 0
A32: M36 | B32: =VLOOKUP(A32,'[1]PRODUCTO NACIONAL'!$A$4:$R$161,6,FALSE) -> Rollo de Galeon 150 ancho | C32: =IFERROR(HLOOKUP(A32,[2]dimensiones_pdfs!$C$3:$Z$5,3,FALSE),0) -> 1.7700001 | D32: =VLOOKUP(A32,'[1]PRODUCTO NACIONAL'!$A$4:$R$161,18,FALSE) -> 0.775 | E32: =-(+C32*D32) -> -1.3717501
A33: M78 | B33: =VLOOKUP(A33,'[1]PRODUCTO NACIONAL'!$A$4:$R$161,6,FALSE) -> PIEL DE DURAZNO | C33: =IFERROR(HLOOKUP(A33,[2]dimensiones_pdfs!$C$3:$Z$5,3,FALSE),0) -> 0 | D33: =VLOOKUP(A33,'[1]PRODUCTO NACIONAL'!$A$4:$R$161,18,FALSE) -> 2.5 | E33: =-(+C33*D33) -> 0
A34: M14 | B34: =VLOOKUP(A34,'[1]PRODUCTO NACIONAL'!$A$4:$R$161,6,FALSE) -> D2002 Rollo Ernest 1.70m x 140gr | C34: =IFERROR(HLOOKUP(A34,[2]dimensiones_pdfs!$C$3:$Z$5,3,FALSE),0) -> 22.172662 | D34: =VLOOKUP(A34,'[1]PRODUCTO NACIONAL'!$A$4:$R$161,18,FALSE) -> 1.4285714 | E34: =-(+C34*D34) -> -31.675231
A35: M28 | B35: =VLOOKUP(A35,'[1]PRODUCTO NACIONAL'!$A$4:$R$161,6,FALSE) -> PRADA LISA | C35: =IFERROR(HLOOKUP(A35,[2]dimensiones_pdfs!$C$3:$Z$5,3,FALSE),0) -> 0 | D35: =VLOOKUP(A35,'[1]PRODUCTO NACIONAL'!$A$4:$R$161,18,FALSE) -> 2.52024 | E35: =-(+C35*D35) -> 0
A36: M34 | B36: =VLOOKUP(A36,'[1]PRODUCTO NACIONAL'!$A$4:$R$161,6,FALSE) -> PRADA ROMBOS|CUADROS | C36: =IFERROR(HLOOKUP(A36,[2]dimensiones_pdfs!$C$3:$Z$5,3,FALSE),0) -> 0 | D36: 2 | E36: =-(+C36*D36) -> 0
A37: M16 | B37: =VLOOKUP(A37,'[1]PRODUCTO NACIONAL'!$A$4:$R$161,6,FALSE) -> D2003 Rollo Pike Deportivo 1.70m x 160gr | C37: =IFERROR(HLOOKUP(A37,[2]dimensiones_pdfs!$C$3:$Z$5,3,FALSE),0) -> 5.8723674 | D37: =VLOOKUP(A37,'[1]PRODUCTO NACIONAL'!$A$4:$R$161,18,FALSE) -> 1.5306122 | E37: =-(+C37*D37) -> -8.9883174
A38: M59 | B38: =VLOOKUP(A38,'[1]PRODUCTO NACIONAL'!$A$4:$R$161,6,FALSE) -> PIKE LACOAST 20 PEI AZUL MARINO| OSCURO | C38: =IFERROR(HLOOKUP(A38,[2]dimensiones_pdfs!$C$3:$Z$5,3,FALSE),0) -> 0 | D38: =VLOOKUP(A38,'[1]PRODUCTO NACIONAL'!$A$4:$R$161,18,FALSE) -> 5.56184 | E38: =-(+C38*D38) -> 0
B43: GASTOS PERSONAL | C43: - | D43: - | E43: =+E66 -> -990.09792
B49: GASTOS PERSONAL
B50: DESCRIPCION | C50: PRECIO | D50: DÍAS | E50: VALOR
B51: CALANDRA | C51: 18 | D51: 6 | E51: =-(+C51*D51) -> -108
B52: LUZ | C52: 12.5 | D52: 6 | E52: =-(+C52*D52) -> -75
B53: PLAN DE CLARO NOVIEMBRE | C53: 20 | D53: 0 | E53: =-(+C53*D53) -> 0
B54: DOMESTICA | C54: =+'DIS. PRENDAS'!L12 -> 25.279583 | D54: 5 | E54: =-(+C54*D54) -> -126.39792
B55: PATTY GERENTE GENERAL | C55: ='DIS. PRENDAS'!R12 -> 36.48125 | D55: 6 | E55: =-(+C55*D55) -> -218.8875
B56: ASISTENTE Dunia GERENTE DE PRODUCCIÓN | C56: =+'DIS. PRENDAS'!O12 -> 31.502778 | D56: 6 | E56: =-(+C56*D56) -> -189.01667
B57: DISEÑADOR Luis | C57: ='DIS. PRENDAS'!L12 -> 25.279583 | D57: 6 | E57: =-(+C57*D57) -> -151.6775
B58: COSTURERO EDGAR | C58: =+'DIS. PRENDAS'!L12 -> 25.279583 | D58: 2.5 | E58: =-(+C58*D58) -> -63.198958
B59: COSTURERA Mami | C59: =+'DIS. PRENDAS'!L12 -> 25.279583 | D59: 1.5 | E59: =-(+C59*D59) -> -37.919375
B60: Costurera Elvia | C60: 20 | D60: 1 | E60: =-(+C60*D60) -> -20
B61: COSTURA EXTERNA | C61: 15 | D61: 0 | E61: =-(+C61*D61) -> 0
B62: CORTADOR-SUBLIMADOR EXTERNO Javier Espinoza | C62: =+'DIS. PRENDAS'!L12 -> 25.279583 | D62: 0 | E62: =-(+C62*D62) -> 0
B63: Corta Hilachas-Planchador-Empaqueta. ANGIE | C63: 20 | D63: 0 | E63: =-(+C63*D63) -> 0
B64: Empareja y Empaqueta Carla Dominguez | C64: 20 | D64: 0 | E64: =-(+C64*D64) -> 0
B65: CONTADORA Janinna Andrade NOVIEMBRE | C65: 25 | E65: =-(+C65*D65) -> 0
E66: =SUM(E51:E65) -> -990.09792
F69: EGRESA
B70: DESCRIPCION | C70: IMPRESIÓN | D70: INGRESA | F70: # POLINES | G70: BORDADO | H70: DTF/TPU | I70: GORRAS | J70: JARRO | K70: CUELLO BORDADOS | L70: PUÑO BORDADOS | M70: ENVIOS | N70: CINTA REFLECTIVA
C71: =SUM(C72:C165) -> 0 | D71: N° ORDEN | E71: =SUM(E72:E165) -> 444.5 | F71: =SUM(F72:F165) -> 15 | G71: =SUM(G72:G165) -> 0 | H71: =SUM(H72:H165) -> 0 | I71: =SUM(I72:I165) -> 0 | J71: =SUM(J72:J165) -> 0 | K71: =SUM(K72:K165) -> 9 | L71: =SUM(L72:L165) -> 9 | ... N71: =SUM(N72:N165) -> 0
B72: MOTORIZADO | D72: GASTOS | M72: 3
B73: PRODUCCION | D73: 5429 | E73: 0 | F73: 20 DISEÑO ANULADA Javier Monserrate de Atletico Bolivar falta listado
B74: PRODUCCION | D74: 6070 | F74: Sacar en Optitex muestras de falda short
B75: PRODUCCION | D75: 6119 | E75: 0 | F75: Generar mockup de niños para la pagina yunpar
B76: PRODUCCION | D76: 6150 | F76: falta orden
B77: PRODUCCION | D77: 6165 | F77: falta orden
B78: PRODUCCION | D78: 6183 | F78: falta orden
B79: PRODUCCION | D79: 6208 | F79: TRAJE JOSE SPIDERMNA
B80: PRODUCCION | D80: 6228 | E80: 40
B81: PRODUCCION | D81: 6229 | E81: 0 | F81: FALTA HACER
B82: PRODUCCION | D82: 6231 | E82: 17
B83: PRODUCCION | D83: 6233 | E83: 14
B84: PRODUCCION | D84: 6234 | E84: 27 | K84: 2 | L84: 2
B85: PRODUCCION | D85: 6235 | E85: 28 | K85: 2 | L85: 2
B86: PRODUCCION | D86: 6236 | E86: 11 | K86: 1 | L86: 1
B87: PRODUCCION | D87: 6237 | E87: 4.5
B88: PRODUCCION | D88: 6238 | E88: 32 | K88: 2 | L88: 2
B89: PRODUCCION | D89: 6239 | E89: 249 | F89: 15
B90: PRODUCCION | D90: 6240 | F90: FALTA HACER
B91: PRODUCCION | D91: 6241 | F91: FALTA HACER
B92: PRODUCCION | D92: 6242 | E92: 22 | K92: 2 | L92: 2

Sheet 97
B2: SEMANA 97 CALANDRA
B3: Lunes 12 ENERO al sábado 17 de ENERO del 2026
B4: INGRESA | E4: =+E71 -> 3662.41
B5: EGRESOS | F5: =SUM(E8:E47) -> -2511.5387
B6: DIFERENCIA | E6: =+E4+F5 -> 1150.8713 | H6: =+E6/E4 -> 0.31423879
A7: ID | B7: EGRESOS | C7: CANTIDAD | D7: VALOR
A8: =IF('[1]PRODUCTO NACIONAL'!A14<>"",'[1]PRODUCTO NACIONAL'!A14,"") -> M11 | B8: =VLOOKUP(A8,'[1]PRODUCTO NACIONAL'!$A$4:$R$161,6,FALSE) -> IMPRESIÓN SIN DISEÑO, ANCHO 1.8X90gsm | C8: =IFERROR(HLOOKUP(A8,[3]dimensiones_pdfs!$C$3:$Z$5,3,FALSE),0) -> 296.71991 | D8: =VLOOKUP(A8,'[1]PRODUCTO NACIONAL'!$A$4:$R$161,18,FALSE) -> 1.3879841 | E8: =-(+C8*D8) -> -411.84251
A9: =IF('[1]PRODUCTO NACIONAL'!A18<>"",'[1]PRODUCTO NACIONAL'!A18,"") -> M15 | B9: =VLOOKUP(A9,'[1]PRODUCTO NACIONAL'!$A$4:$R$161,6,FALSE) -> D2006 Rollo Panal 1.70m x 160gr | C9: =IFERROR(HLOOKUP(A9,[3]dimensiones_pdfs!$C$3:$Z$5,3,FALSE),0) -> 49.316159 | D9: =VLOOKUP(A9,'[1]PRODUCTO NACIONAL'!$A$4:$R$161,18,FALSE) -> 1.6348774 | E9: =-(+C9*D9) -> -80.625874
A10: =IF('[1]PRODUCTO NACIONAL'!A27<>"",'[1]PRODUCTO NACIONAL'!A27,"") -> M24 | B10: =IF('[1]PRODUCTO NACIONAL'!F27<>"",'[1]PRODUCTO NACIONAL'!F27,"") -> POLIN GUTMAN T8-10 | T10-12 | C10: =F71 -> 159 | D10: =IF('[1]PRODUCTO NACIONAL'!R27<>"",'[1]PRODUCTO NACIONAL'!R27,"") -> 1.925065 | E10: =-(+C10*D10) -> -306.08533
B11: =+G70 -> BORDADO | C11: =G71 -> 0 | D11: 1 | E11: =-(+C11*D11) -> 0
B12: =+H70 -> DTF/TPU | C12: =H71 -> 35 | D12: 1 | E12: =-(+C12*D12) -> -35
B13: =+I70 -> GORRAS | C13: =I71 -> 0 | D13: 2 | E13: =-(+C13*D13) -> 0
B14: =+J70 -> JARRO | C14: =J71 -> 0 | E14: =-(+C14*D14) -> 0
A15: =IF('[1]PRODUCTO NACIONAL'!A67<>"",'[1]PRODUCTO NACIONAL'!A67,"") -> M64 | B15: =IF('[1]PRODUCTO NACIONAL'!F67<>"",'[1]PRODUCTO NACIONAL'!F67,"") -> CUELLOS20 PEI|NEGRO AZABACHE Y MAS. | C15: =K71 -> 6 | D15: =VLOOKUP(A15,'[1]PRODUCTO NACIONAL'!$A$4:$R$161,18,FALSE) -> 0.47644606 | E15: =-(+C15*D15) -> -2.8586764
A16: =IF('[1]PRODUCTO NACIONAL'!A68<>"",'[1]PRODUCTO NACIONAL'!A68,"") -> M65 | B16: =IF('[1]PRODUCTO NACIONAL'!F68<>"",'[1]PRODUCTO NACIONAL'!F68,"") -> PUÑOS20 PEI|NEGRO AZABACHE Y MAS. | C16: =L71 -> 6 | D16: =VLOOKUP(A16,'[1]PRODUCTO NACIONAL'!$A$4:$R$161,18,FALSE) -> 0.23822303 | E16: =-(+C16*D16) -> -1.4293382
B17: =+M70 -> ENVIOS | C17: =M71 -> 8 | D17: 1 | E17: =-(+C17*D17) -> -8
A18: =IF('[1]PRODUCTO NACIONAL'!A76<>"",'[1]PRODUCTO NACIONAL'!A76,"") -> M73 | B18: =IF('[1]PRODUCTO NACIONAL'!F76<>"",'[1]PRODUCTO NACIONAL'!F76,"") -> CINTA REFLECTIVA DE 3cm de anchox1m | C18: =N71 -> 0 | D18: =VLOOKUP(A18,'[1]PRODUCTO NACIONAL'!$A$4:$R$161,18,FALSE) -> 1.3999945 | E18: =-(+C18*D18) -> 0
A19: =IF('[1]PRODUCTO NACIONAL'!A28<>"",'[1]PRODUCTO NACIONAL'!A28,"") -> M25 | B19: =VLOOKUP(A19,'[1]PRODUCTO NACIONAL'!$A$4:$R$161,6,FALSE) -> ALGODÓN ARUBA PEI AZUL MARINO| COLORES| BLANCO | C19: =IFERROR(HLOOKUP(A19,[3]dimensiones_pdfs!$C$3:$Z$5,3,FALSE),0) -> 0 | D19: =VLOOKUP(A19,'[1]PRODUCTO NACIONAL'!$A$4:$R$161,18,FALSE) -> 4.8341953 | E19: =-(+C19*D19) -> 0
A20: M61 | B20: =VLOOKUP(A20,'[1]PRODUCTO NACIONAL'!$A$4:$R$161,6,FALSE) -> INTERLOCK 40 SPUN 1.2 BLANCO FROZEN | C20: =IFERROR(HLOOKUP(A20,[3]dimensiones_pdfs!$C$3:$Z$5,3,FALSE),0) -> 2.3655136 | D20: =VLOOKUP(A20,'[1]PRODUCTO NACIONAL'!$A$4:$R$161,18,FALSE) -> 4.2071437 | E20: =-(+C20*D20) -> -9.9520558
A21: =IF('[1]PRODUCTO NACIONAL'!A61<>"",'[1]PRODUCTO NACIONAL'!A61,"") -> M58 | B21: =VLOOKUP(A21,'[1]PRODUCTO NACIONAL'!$A$4:$R$161,6,FALSE) -> PIKE LACOAST 20 PEI CELESTE| CLARO | C21: =IFERROR(HLOOKUP(A21,[3]dimensiones_pdfs!$C$3:$Z$5,3,FALSE),0) -> 0 | D21: =VLOOKUP(A21,'[1]PRODUCTO NACIONAL'!$A$4:$R$161,18,FALSE) -> 4.9712 | E21: =-(+C21*D21) -> 0
A22: =IF('[1]PRODUCTO NACIONAL'!A62<>"",'[1]PRODUCTO NACIONAL'!A62,"") -> M59 | B22: =VLOOKUP(A22,'[1]PRODUCTO NACIONAL'!$A$4:$R$161,6,FALSE) -> PIKE LACOAST 20 PEI AZUL MARINO| OSCURO | C22: =IFERROR(HLOOKUP(A22,[3]dimensiones_pdfs!$C$3:$Z$5,3,FALSE),0) -> 0 | D22: =VLOOKUP(A22,'[1]PRODUCTO NACIONAL'!$A$4:$R$161,18,FALSE) -> 5.56184 | E22: =-(+C22*D22) -> 0
A23: =IF('[1]PRODUCTO NACIONAL'!A21<>"",'[1]PRODUCTO NACIONAL'!A21,"") -> M18 | B23: =VLOOKUP(A23,'[1]PRODUCTO NACIONAL'!$A$4:$R$161,6,FALSE) -> RIBB 150TEX COLORES| POLIESTER | C23: =IFERROR(HLOOKUP(A23,[3]dimensiones_pdfs!$C$3:$Z$5,3,FALSE),0)+1 -> 2.3581335 | D23: =VLOOKUP(A23,'[1]PRODUCTO NACIONAL'!$A$4:$R$161,18,FALSE) -> 2.1063822 | E23: =-(+C23*D23) -> -4.9671305
A24: =IF('[1]PRODUCTO NACIONAL'!A78<>"",'[1]PRODUCTO NACIONAL'!A78,"") -> M75 | B24: =VLOOKUP(A24,'[1]PRODUCTO NACIONAL'!$A$4:$R$161,6,FALSE) -> Ribb Lugano 100% POLIESTER | C24: =IFERROR(HLOOKUP(A24,[3]dimensiones_pdfs!$C$3:$Z$5,3,FALSE),0) -> 0 | D24: =VLOOKUP(A24,'[1]PRODUCTO NACIONAL'!$A$4:$R$161,18,FALSE) -> 4.5378 | E24: =-(+C24*D24) -> 0
A25: =IF('[1]PRODUCTO NACIONAL'!A30<>"",'[1]PRODUCTO NACIONAL'!A30,"") -> M27 | B25: =VLOOKUP(A25,'[1]PRODUCTO NACIONAL'!$A$4:$R$161,6,FALSE) -> VIOTO PESADA BLANCA|NEGRO|NARANJA FOSFORESCENTE | C25: =IFERROR(HLOOKUP(A25,[3]dimensiones_pdfs!$C$3:$Z$5,3,FALSE),0) -> 43.58631 | D25: =VLOOKUP(A25,'[1]PRODUCTO NACIONAL'!$A$4:$R$161,18,FALSE) -> 1.9499895 | E25: =-(+C25*D25) -> -84.992847
A26: =IF('[1]PRODUCTO NACIONAL'!A22<>"",'[1]PRODUCTO NACIONAL'!A22,"") -> M19 | B26: =VLOOKUP(A26,'[1]PRODUCTO NACIONAL'!$A$4:$R$161,6,FALSE) -> RIVER TEX NEGRO|COLORES | C26: =IFERROR(HLOOKUP(A26,[3]dimensiones_pdfs!$C$3:$Z$5,3,FALSE),0) -> 0 | D26: =VLOOKUP(A26,'[1]PRODUCTO NACIONAL'!$A$4:$R$161,18,FALSE) -> 2.4101474 | E26: =-(+C26*D26) -> 0
A27: =IF('[1]PRODUCTO NACIONAL'!A15<>"",'[1]PRODUCTO NACIONAL'!A15,"") -> M12 | B27: =VLOOKUP(A27,'[1]PRODUCTO NACIONAL'!$A$4:$R$161,6,FALSE) -> LINO JARUBA | C27: =IFERROR(HLOOKUP(A27,[3]dimensiones_pdfs!$C$3:$Z$5,3,FALSE),0) -> 0 | D27: =VLOOKUP(A27,'[1]PRODUCTO NACIONAL'!$A$4:$R$161,18,FALSE) -> 1.8905 | E27: =-(+C27*D27) -> 0
A28: =+'[1]PRODUCTO NACIONAL'!$A$4 -> M1 | B28: =VLOOKUP(A28,'[1]PRODUCTO NACIONAL'!$A$4:$R$161,6,FALSE) -> NYLON | C28: =IFERROR(HLOOKUP(A28,[3]dimensiones_pdfs!$C$3:$Z$5,3,FALSE),0) -> 2.9505187 | D28: =VLOOKUP(A28,'[1]PRODUCTO NACIONAL'!$A$4:$R$161,18,FALSE) -> 1.78999 | E28: =-(+C28*D28) -> -5.281399
A29: M17 | B29: =VLOOKUP(A29,'[1]PRODUCTO NACIONAL'!$A$4:$R$161,6,FALSE) -> D2008 Rollo Jersy Spandex 1.80m x 275gr | C29: =IFERROR(HLOOKUP(A29,[3]dimensiones_pdfs!$C$3:$Z$5,3,FALSE),0) -> 3.6744757 | D29: =VLOOKUP(A29,'[1]PRODUCTO NACIONAL'!$A$4:$R$161,18,FALSE) -> 3.4782609 | E29: =-(+C29*D29) -> -12.780785
A30: M35 | B30: =VLOOKUP(A30,'[1]PRODUCTO NACIONAL'!$A$4:$R$161,6,FALSE) -> NICO SPORT|BLANCO | C30: =IFERROR(HLOOKUP(A30,[3]dimensiones_pdfs!$C$3:$Z$5,3,FALSE),0) -> 0 | D30: =VLOOKUP(A30,'[1]PRODUCTO NACIONAL'!$A$4:$R$161,18,FALSE) -> 2.316 | E30: =-(+C30*D30) -> 0
A31: M37 | B31: =VLOOKUP(A31,'[1]PRODUCTO NACIONAL'!$A$4:$R$161,6,FALSE) -> MURRAY|BLANCA | C31: =IFERROR(HLOOKUP(A31,[3]dimensiones_pdfs!$C$3:$Z$5,3,FALSE),0) -> 0 | D31: =VLOOKUP(A31,'[1]PRODUCTO NACIONAL'!$A$4:$R$161,18,FALSE) -> 2.2825013 | E31: =-(+C31*D31) -> 0
A32: M36 | B32: =VLOOKUP(A32,'[1]PRODUCTO NACIONAL'!$A$4:$R$161,6,FALSE) -> Rollo de Galeon 150 ancho | C32: =IFERROR(HLOOKUP(A32,[3]dimensiones_pdfs!$C$3:$Z$5,3,FALSE),0) -> 2.0199998 | D32: =VLOOKUP(A32,'[1]PRODUCTO NACIONAL'!$A$4:$R$161,18,FALSE) -> 0.775 | E32: =-(+C32*D32) -> -1.5654998
A33: M78 | B33: =VLOOKUP(A33,'[1]PRODUCTO NACIONAL'!$A$4:$R$161,6,FALSE) -> PIEL DE DURAZNO | C33: =IFERROR(HLOOKUP(A33,[3]dimensiones_pdfs!$C$3:$Z$5,3,FALSE),0) -> 0 | D33: =VLOOKUP(A33,'[1]PRODUCTO NACIONAL'!$A$4:$R$161,18,FALSE) -> 2.5 | E33: =-(+C33*D33) -> 0
A34: M14 | B34: =VLOOKUP(A34,'[1]PRODUCTO NACIONAL'!$A$4:$R$161,6,FALSE) -> D2002 Rollo Ernest 1.70m x 140gr | C34: =IFERROR(HLOOKUP(A34,[3]dimensiones_pdfs!$C$3:$Z$5,3,FALSE),0) -> 110.70057 | D34: =VLOOKUP(A34,'[1]PRODUCTO NACIONAL'!$A$4:$R$161,18,FALSE) -> 1.4285714 | E34: =-(+C34*D34) -> -158.14367
A35: M28 | B35: =VLOOKUP(A35,'[1]PRODUCTO NACIONAL'!$A$4:$R$161,6,FALSE) -> PRADA LISA | C35: =IFERROR(HLOOKUP(A35,[3]dimensiones_pdfs!$C$3:$Z$5,3,FALSE),0) -> 0 | D35: =VLOOKUP(A35,'[1]PRODUCTO NACIONAL'!$A$4:$R$161,18,FALSE) -> 2.52024 | E35: =-(+C35*D35) -> 0
A36: M34 | B36: =VLOOKUP(A36,'[1]PRODUCTO NACIONAL'!$A$4:$R$161,6,FALSE) -> PRADA ROMBOS|CUADROS | C36: =IFERROR(HLOOKUP(A36,[3]dimensiones_pdfs!$C$3:$Z$5,3,FALSE),0) -> 0 | D36: 2 | E36: =-(+C36*D36) -> 0
A37: M16 | B37: =VLOOKUP(A37,'[1]PRODUCTO NACIONAL'!$A$4:$R$161,6,FALSE) -> D2003 Rollo Pike Deportivo 1.70m x 160gr | C37: =IFERROR(HLOOKUP(A37,[3]dimensiones_pdfs!$C$3:$Z$5,3,FALSE),0) -> 66.324938 | D37: =VLOOKUP(A37,'[1]PRODUCTO NACIONAL'!$A$4:$R$161,18,FALSE) -> 1.5306122 | E37: =-(+C37*D37) -> -101.51776
A38: M59 | B38: =VLOOKUP(A38,'[1]PRODUCTO NACIONAL'!$A$4:$R$161,6,FALSE) -> PIKE LACOAST 20 PEI AZUL MARINO| OSCURO | C38: =IFERROR(HLOOKUP(A38,[3]dimensiones_pdfs!$C$3:$Z$5,3,FALSE),0) -> 0 | D38: =VLOOKUP(A38,'[1]PRODUCTO NACIONAL'!$A$4:$R$161,18,FALSE) -> 5.56184 | E38: =-(+C38*D38) -> 0
B43: GASTOS PERSONAL | C43: - | D43: - | E43: =+E66 -> -1286.4958
B49: GASTOS PERSONAL
B50: DESCRIPCION | C50: PRECIO | D50: DÍAS | E50: VALOR
B51: CALANDRA | C51: 18 | D51: 6 | E51: =-(+C51*D51) -> -108
B52: LUZ | C52: 12.5 | D52: 6 | E52: =-(+C52*D52) -> -75
B53: PLAN DE CLARO NOVIEMBRE | C53: 15 | D53: 1 | E53: =-(+C53*D53) -> -15
B54: DOMESTICA | C54: =+'DIS. PRENDAS'!L12 -> 25.279583 | D54: 5 | E54: =-(+C54*D54) -> -126.39792
B55: PATTY GERENTE GENERAL | C55: ='DIS. PRENDAS'!R12 -> 36.48125 | D55: 6 | E55: =-(+C55*D55) -> -218.8875
B56: ASISTENTE Dunia GERENTE DE PRODUCCIÓN | C56: =+'DIS. PRENDAS'!O12 -> 31.502778 | D56: 6 | E56: =-(+C56*D56) -> -189.01667
B57: DISEÑADOR Luis | C57: ='DIS. PRENDAS'!L12 -> 25.279583 | D57: 6 | E57: =-(+C57*D57) -> -151.6775
B58: COSTURERO EDGAR | C58: =+'DIS. PRENDAS'!L12 -> 25.279583 | D58: 4 | E58: =-(+C58*D58) -> -101.11833
B59: COSTURERA Mami | C59: =+'DIS. PRENDAS'!L12 -> 25.279583 | D59: 5 | E59: =-(+C59*D59) -> -126.39792
B60: Costurera Elvia | C60: 20 | D60: 4 | E60: =-(+C60*D60) -> -80
B61: COSTURA EXTERNA | C61: 15 | D61: 0 | E61: =-(+C61*D61) -> 0
B62: CORTADOR-SUBLIMADOR EXTERNO Javier Espinoza | C62: =+'DIS. PRENDAS'!L12 -> 25.279583 | D62: 0 | E62: =-(+C62*D62) -> 0
B63: Corta Hilachas-Planchador-Empaqueta. ANGIE | C63: 20 | D63: 3.5 | E63: =-(+C63*D63) -> -70
B64: Empareja y Empaqueta Carla Dominguez | C64: 20 | D64: 0 | E64: =-(+C64*D64) -> 0
B65: CONTADORA Janinna Andrade NOVIEMBRE | C65: 25 | D65: 1 | E65: =-(+C65*D65) -> -25
E66: =SUM(E51:E65) -> -1286.4958
F69: EGRESA
B70: DESCRIPCION | C70: IMPRESIÓN | D70: INGRESA | F70: # POLINES | G70: BORDADO | H70: DTF/TPU | I70: GORRAS | J70: JARRO | K70: CUELLO BORDADOS | L70: PUÑO BORDADOS | M70: ENVIOS | N70: CINTA REFLECTIVA | O70: GASTOS VARIOS
C71: =SUM(C72:C306) -> 0 | D71: N° ORDEN | E71: =SUM(E72:E306) -> 3662.41 | F71: =SUM(F72:F306) -> 159 | G71: =SUM(G72:G306) -> 0 | H71: =SUM(H72:H306) -> 35 | I71: =SUM(I72:I306) -> 0 | J71: =SUM(J72:J306) -> 0 | K71: =SUM(K72:K306) -> 6 | L71: =SUM(L72:L306) -> 6 | ... O71: =SUM(O72:O306) -> 118.4
B72: MOTORIZADO | D72: GASTOS | M72: 3
B73: sublime store banderas | D73: SIN ORDEN | E73: 10.23
B74: MOTORIZADO MOTO FAST POLINES | D74: LOGIST. | M74: 5
B75: REATA Y ELASTICO DE PANTALONETAS GEMSY | D75: COMPRA | O75: 31
B76: CINTA DE PAPEL | D76: COMPRA | O76: 2
B77: MOTOSERVICIO | D77: COMPRA | O77: 2.5
B78: GEMSY JUEGO CUCHILLAS BROCHES | D78: COMPRA | O78: 11.5
B79: BIDONES DE AGUA | D79: COMPRA | O79: 11.75
B80: COMERCIAL GALVEZ 1 BULTO DE FUNDAS 1 B. DE PAPEL H. | D80: COMPRA | O80: 37.4
B81: Gemsy 5 tizas de cera | D81: COMPRA | O81: 3
B82: Moto Fast entrea tizas y Polines en la FIC | D82: COMPRA | O82: 5
B83: Cuellos negros | D83: COMPRA | O83: 3
B84: Recarga Celulares | D84: COMPRA | O84: =5.15+1.1 -> 6.25
B85: Fllete de Tela Carga pesada | D85: COMPRA | O85: 5
B86: PRODUCCION | D86: 5429 | E86: 0 | F86: 20 DISEÑO ANULADA Javier Monserrate de Atletico Bolivar falta listado
B87: PRODUCCION | D87: 6070 | F87: Sacar en Optitex muestras de falda short
B88: PRODUCCION | D88: 6119 | E88: 0 | F88: Generar mockup de niños para la pagina yunpar
B89: PRODUCCION | D89: 6150 | F89: Molde Falda Short mitad plizado
B90: PRODUCCION | D90: 6165 | E90: 319 | F90: 17
B91: PRODUCCION | D91: 6183 | E91: 0 | F91: completar las tiras de ribb y colocar etiquetas que combines con polines y colores CMYK
B92: PRODUCCION | D92: 6208 | E92: 0 | F92: TRAJE JOSE SPIDERMNA
B93: PRODUCCION | D93: 6229 | E93: 306 | F93: 16
B94: PRODUCCION | D94: 6240 | E94: 187 | H94: 35
B95: PRODUCCION | D95: 6241 | E95: 604.5 | F95: 38
B96: PRODUCCION | D96: 6243 | E96: 10 | F96: Diseño Abg. Omar Torres
B97: Yommi equipo futbol ORDEN 6244 + $10 DISEÑO + ARMADO | D97: 6244 | E97: 158.68
B98: PRODUCCION | D98: 6245 | E98: =440*0.6 -> 264 | F98: Garcia Moreno 440 tiras para calentadores o 880 unidades cada una ha 0.3 ctvs.
B99: PRODUCCION | D99: 6246 | E99: 194 | F99: 12
B100: PRODUCCION | D100: 6247 | E100: 24 | K100: 2 | L100: 2
B101: PRODUCCION | D101: 6248 | E101: 11 | K101: 1 | L101: 1
B102: PRODUCCION | D102: 6249 | E102: 43
B103: PRODUCCION | D103: 6250 | E103: 369 | F103: 22
B104: PRODUCCION | D104: 6251 | E104: 766 | F104: 47
B105: PRODUCCION | D105: 6252 | E105: 30
B106: PRODUCCION | D106: 6253 | E106: =140*0.6 -> 84 | F106: Servio Serrano 140 Tiras x 0.6
B107: PRODUCCION | D107: 6254 | E107: 9
B108: PRODUCCION | D108: 6255 | E108: 22 | K108: 2 | L108: 2
B109: PRODUCCION | D109: 6256 | E109: 119 | F109: 4
B110: PRODUCCION | D110: 6257 | E110: 16 | F110: 1
B111: PRODUCCION | D111: 6258 | E111: 40 | F111: 2
B112: PRODUCCION | D112: 6259 | E112: 0 | F112: ANULADA
...

Sheet 98
B2: SEMANA 98 CALANDRA
B3: Lunes 19 ENERO al sábado 24 de ENERO del 2026
B4: INGRESA | E4: =+E71 -> 720.92
B5: EGRESOS | F5: =SUM(E8:E47) -> -1301.1667
B6: DIFERENCIA | E6: =+E4+F5 -> -580.24673 | H6: =+E6/E4 -> -0.80486979
A7: ID | B7: EGRESOS | C7: CANTIDAD | D7: VALOR
A8: =IF('[1]PRODUCTO NACIONAL'!A14<>"",'[1]PRODUCTO NACIONAL'!A14,"") -> M11 | B8: =VLOOKUP(A8,'[1]PRODUCTO NACIONAL'!$A$4:$R$161,6,FALSE) -> IMPRESIÓN SIN DISEÑO, ANCHO 1.8X90gsm | C8: =IFERROR(HLOOKUP(A8,[4]dimensiones_pdfs!$C$3:$Z$5,3,FALSE),0) -> 59.833519 | D8: =VLOOKUP(A8,'[1]PRODUCTO NACIONAL'!$A$4:$R$161,18,FALSE) -> 1.3879841 | E8: =-(+C8*D8) -> -83.04797
A9: =IF('[1]PRODUCTO NACIONAL'!A18<>"",'[1]PRODUCTO NACIONAL'!A18,"") -> M15 | B9: =VLOOKUP(A9,'[1]PRODUCTO NACIONAL'!$A$4:$R$161,6,FALSE) -> D2006 Rollo Panal 1.70m x 160gr | C9: =IFERROR(HLOOKUP(A9,[4]dimensiones_pdfs!$C$3:$Z$5,3,FALSE),0) -> 11.213983 | D9: =VLOOKUP(A9,'[1]PRODUCTO NACIONAL'!$A$4:$R$161,18,FALSE) -> 1.6348774 | E9: =-(+C9*D9) -> -18.333488
A10: =IF('[1]PRODUCTO NACIONAL'!A27<>"",'[1]PRODUCTO NACIONAL'!A27,"") -> M24 | B10: =IF('[1]PRODUCTO NACIONAL'!F27<>"",'[1]PRODUCTO NACIONAL'!F27,"") -> POLIN GUTMAN T8-10 | T10-12 | C10: =F71 -> 25 | D10: =IF('[1]PRODUCTO NACIONAL'!R27<>"",'[1]PRODUCTO NACIONAL'!R27,"") -> 1.925065 | E10: =-(+C10*D10) -> -48.126625
B11: =+G70 -> BORDADO | C11: =G71 -> 0 | D11: 1 | E11: =-(+C11*D11) -> 0
B12: =+H70 -> DTF/TPU | C12: =H71 -> 0 | D12: 1 | E12: =-(+C12*D12) -> 0
B13: =+I70 -> GORRAS | C13: =I71 -> 0 | D13: 2 | E13: =-(+C13*D13) -> 0
B14: =+J70 -> JARRO | C14: =J71 -> 0 | E14: =-(+C14*D14) -> 0
A15: =IF('[1]PRODUCTO NACIONAL'!A67<>"",'[1]PRODUCTO NACIONAL'!A67,"") -> M64 | B15: =IF('[1]PRODUCTO NACIONAL'!F67<>"",'[1]PRODUCTO NACIONAL'!F67,"") -> CUELLOS20 PEI|NEGRO AZABACHE Y MAS. | C15: =K71 -> 4 | D15: =VLOOKUP(A15,'[1]PRODUCTO NACIONAL'!$A$4:$R$161,18,FALSE) -> 0.47644606 | E15: =-(+C15*D15) -> -1.9057842
A16: =IF('[1]PRODUCTO NACIONAL'!A68<>"",'[1]PRODUCTO NACIONAL'!A68,"") -> M65 | B16: =IF('[1]PRODUCTO NACIONAL'!F68<>"",'[1]PRODUCTO NACIONAL'!F68,"") -> PUÑOS20 PEI|NEGRO AZABACHE Y MAS. | C16: =L71 -> 4 | D16: =VLOOKUP(A16,'[1]PRODUCTO NACIONAL'!$A$4:$R$161,18,FALSE) -> 0.23822303 | E16: =-(+C16*D16) -> -0.95289212
B17: =+M70 -> ENVIOS | C17: =M71 -> 7.5 | D17: 1 | E17: =-(+C17*D17) -> -7.5
A18: =IF('[1]PRODUCTO NACIONAL'!A76<>"",'[1]PRODUCTO NACIONAL'!A76,"") -> M73 | B18: =IF('[1]PRODUCTO NACIONAL'!F76<>"",'[1]PRODUCTO NACIONAL'!F76,"") -> CINTA REFLECTIVA DE 3cm de anchox1m | C18: =N71 -> 0 | D18: =VLOOKUP(A18,'[1]PRODUCTO NACIONAL'!$A$4:$R$161,18,FALSE) -> 1.3999945 | E18: =-(+C18*D18) -> 0
A19: =IF('[1]PRODUCTO NACIONAL'!A28<>"",'[1]PRODUCTO NACIONAL'!A28,"") -> M25 | B19: =VLOOKUP(A19,'[1]PRODUCTO NACIONAL'!$A$4:$R$161,6,FALSE) -> ALGODÓN ARUBA PEI AZUL MARINO| COLORES| BLANCO | C19: =IFERROR(HLOOKUP(A19,[4]dimensiones_pdfs!$C$3:$Z$5,3,FALSE),0) -> 0 | D19: =VLOOKUP(A19,'[1]PRODUCTO NACIONAL'!$A$4:$R$161,18,FALSE) -> 4.8341953 | E19: =-(+C19*D19) -> 0
A20: M61 | B20: =VLOOKUP(A20,'[1]PRODUCTO NACIONAL'!$A$4:$R$161,6,FALSE) -> INTERLOCK 40 SPUN 1.2 BLANCO FROZEN | C20: =IFERROR(HLOOKUP(A20,[4]dimensiones_pdfs!$C$3:$Z$5,3,FALSE),0) -> 0 | D20: =VLOOKUP(A20,'[1]PRODUCTO NACIONAL'!$A$4:$R$161,18,FALSE) -> 4.2071437 | E20: =-(+C20*D20) -> 0
A21: =IF('[1]PRODUCTO NACIONAL'!A61<>"",'[1]PRODUCTO NACIONAL'!A61,"") -> M58 | B21: =VLOOKUP(A21,'[1]PRODUCTO NACIONAL'!$A$4:$R$161,6,FALSE) -> PIKE LACOAST 20 PEI CELESTE| CLARO | C21: =IFERROR(HLOOKUP(A21,[4]dimensiones_pdfs!$C$3:$Z$5,3,FALSE),0) -> 0 | D21: =VLOOKUP(A21,'[1]PRODUCTO NACIONAL'!$A$4:$R$161,18,FALSE) -> 4.9712 | E21: =-(+C21*D21) -> 0
A22: =IF('[1]PRODUCTO NACIONAL'!A62<>"",'[1]PRODUCTO NACIONAL'!A62,"") -> M59 | B22: =VLOOKUP(A22,'[1]PRODUCTO NACIONAL'!$A$4:$R$161,6,FALSE) -> PIKE LACOAST 20 PEI AZUL MARINO| OSCURO | C22: =IFERROR(HLOOKUP(A22,[4]dimensiones_pdfs!$C$3:$Z$5,3,FALSE),0) -> 0 | D22: =VLOOKUP(A22,'[1]PRODUCTO NACIONAL'!$A$4:$R$161,18,FALSE) -> 5.56184 | E22: =-(+C22*D22) -> 0
A23: =IF('[1]PRODUCTO NACIONAL'!A21<>"",'[1]PRODUCTO NACIONAL'!A21,"") -> M18 | B23: =VLOOKUP(A23,'[1]PRODUCTO NACIONAL'!$A$4:$R$161,6,FALSE) -> RIBB 150TEX COLORES| POLIESTER | C23: =IFERROR(HLOOKUP(A23,[4]dimensiones_pdfs!$C$3:$Z$5,3,FALSE),0) -> 0.11478549 | D23: =VLOOKUP(A23,'[1]PRODUCTO NACIONAL'!$A$4:$R$161,18,FALSE) -> 2.1063822 | E23: =-(+C23*D23) -> -0.24178212
A24: =IF('[1]PRODUCTO NACIONAL'!A78<>"",'[1]PRODUCTO NACIONAL'!A78,"") -> M75 | B24: =VLOOKUP(A24,'[1]PRODUCTO NACIONAL'!$A$4:$R$161,6,FALSE) -> Ribb Lugano 100% POLIESTER | C24: =IFERROR(HLOOKUP(A24,[4]dimensiones_pdfs!$C$3:$Z$5,3,FALSE),0) -> 0 | D24: =VLOOKUP(A24,'[1]PRODUCTO NACIONAL'!$A$4:$R$161,18,FALSE) -> 4.5378 | E24: =-(+C24*D24) -> 0
A25: =IF('[1]PRODUCTO NACIONAL'!A30<>"",'[1]PRODUCTO NACIONAL'!A30,"") -> M27 | B25: =VLOOKUP(A25,'[1]PRODUCTO NACIONAL'!$A$4:$R$161,6,FALSE) -> VIOTO PESADA BLANCA|NEGRO|NARANJA FOSFORESCENTE | C25: =IFERROR(HLOOKUP(A25,[4]dimensiones_pdfs!$C$3:$Z$5,3,FALSE),0) -> 0 | D25: =VLOOKUP(A25,'[1]PRODUCTO NACIONAL'!$A$4:$R$161,18,FALSE) -> 1.9499895 | E25: =-(+C25*D25) -> 0
A26: =IF('[1]PRODUCTO NACIONAL'!A22<>"",'[1]PRODUCTO NACIONAL'!A22,"") -> M19 | B26: =VLOOKUP(A26,'[1]PRODUCTO NACIONAL'!$A$4:$R$161,6,FALSE) -> RIVER TEX NEGRO|COLORES | C26: =IFERROR(HLOOKUP(A26,[4]dimensiones_pdfs!$C$3:$Z$5,3,FALSE),0) -> 0 | D26: =VLOOKUP(A26,'[1]PRODUCTO NACIONAL'!$A$4:$R$161,18,FALSE) -> 2.4101474 | E26: =-(+C26*D26) -> 0
A27: =IF('[1]PRODUCTO NACIONAL'!A15<>"",'[1]PRODUCTO NACIONAL'!A15,"") -> M12 | B27: =VLOOKUP(A27,'[1]PRODUCTO NACIONAL'!$A$4:$R$161,6,FALSE) -> LINO JARUBA | C27: =IFERROR(HLOOKUP(A27,[4]dimensiones_pdfs!$C$3:$Z$5,3,FALSE),0) -> 0 | D27: =VLOOKUP(A27,'[1]PRODUCTO NACIONAL'!$A$4:$R$161,18,FALSE) -> 1.8905 | E27: =-(+C27*D27) -> 0
A28: =+'[1]PRODUCTO NACIONAL'!$A$4 -> M1 | B28: =VLOOKUP(A28,'[1]PRODUCTO NACIONAL'!$A$4:$R$161,6,FALSE) -> NYLON | C28: =IFERROR(HLOOKUP(A28,[4]dimensiones_pdfs!$C$3:$Z$5,3,FALSE),0) -> 0 | D28: =VLOOKUP(A28,'[1]PRODUCTO NACIONAL'!$A$4:$R$161,18,FALSE) -> 1.78999 | E28: =-(+C28*D28) -> 0
A29: M17 | B29: =VLOOKUP(A29,'[1]PRODUCTO NACIONAL'!$A$4:$R$161,6,FALSE) -> D2008 Rollo Jersy Spandex 1.80m x 275gr | C29: =IFERROR(HLOOKUP(A29,[4]dimensiones_pdfs!$C$3:$Z$5,3,FALSE),0) -> 0 | D29: =VLOOKUP(A29,'[1]PRODUCTO NACIONAL'!$A$4:$R$161,18,FALSE) -> 3.4782609 | E29: =-(+C29*D29) -> 0
A30: M35 | B30: =VLOOKUP(A30,'[1]PRODUCTO NACIONAL'!$A$4:$R$161,6,FALSE) -> NICO SPORT|BLANCO | C30: =IFERROR(HLOOKUP(A30,[4]dimensiones_pdfs!$C$3:$Z$5,3,FALSE),0) -> 0 | D30: =VLOOKUP(A30,'[1]PRODUCTO NACIONAL'!$A$4:$R$161,18,FALSE) -> 2.316 | E30: =-(+C30*D30) -> 0
A31: M37 | B31: =VLOOKUP(A31,'[1]PRODUCTO NACIONAL'!$A$4:$R$161,6,FALSE) -> MURRAY|BLANCA | C31: =IFERROR(HLOOKUP(A31,[4]dimensiones_pdfs!$C$3:$Z$5,3,FALSE),0) -> 0 | D31: =VLOOKUP(A31,'[1]PRODUCTO NACIONAL'!$A$4:$R$161,18,FALSE) -> 2.2825013 | E31: =-(+C31*D31) -> 0
A32: M36 | B32: =VLOOKUP(A32,'[1]PRODUCTO NACIONAL'!$A$4:$R$161,6,FALSE) -> Rollo de Galeon 150 ancho | C32: =IFERROR(HLOOKUP(A32,[4]dimensiones_pdfs!$C$3:$Z$5,3,FALSE),0) -> 7.3363607 | D32: =VLOOKUP(A32,'[1]PRODUCTO NACIONAL'!$A$4:$R$161,18,FALSE) -> 0.775 | E32: =-(+C32*D32) -> -5.6856795
A33: M78 | B33: =VLOOKUP(A33,'[1]PRODUCTO NACIONAL'!$A$4:$R$161,6,FALSE) -> PIEL DE DURAZNO | C33: =IFERROR(HLOOKUP(A33,[4]dimensiones_pdfs!$C$3:$Z$5,3,FALSE),0) -> 0 | D33: =VLOOKUP(A33,'[1]PRODUCTO NACIONAL'!$A$4:$R$161,18,FALSE) -> 2.5 | E33: =-(+C33*D33) -> 0
A34: M14 | B34: =VLOOKUP(A34,'[1]PRODUCTO NACIONAL'!$A$4:$R$161,6,FALSE) -> D2002 Rollo Ernest 1.70m x 140gr | C34: =IFERROR(HLOOKUP(A34,[4]dimensiones_pdfs!$C$3:$Z$5,3,FALSE),0) -> 12.418262 | D34: =VLOOKUP(A34,'[1]PRODUCTO NACIONAL'!$A$4:$R$161,18,FALSE) -> 1.4285714 | E34: =-(+C34*D34) -> -17.740374
A35: M28 | B35: =VLOOKUP(A35,'[1]PRODUCTO NACIONAL'!$A$4:$R$161,6,FALSE) -> PRADA LISA | C35: =IFERROR(HLOOKUP(A35,[4]dimensiones_pdfs!$C$3:$Z$5,3,FALSE),0) -> 0 | D35: =VLOOKUP(A35,'[1]PRODUCTO NACIONAL'!$A$4:$R$161,18,FALSE) -> 2.52024 | E35: =-(+C35*D35) -> 0
A36: M34 | B36: =VLOOKUP(A36,'[1]PRODUCTO NACIONAL'!$A$4:$R$161,6,FALSE) -> PRADA ROMBOS|CUADROS | C36: =IFERROR(HLOOKUP(A36,[4]dimensiones_pdfs!$C$3:$Z$5,3,FALSE),0) -> 0 | D36: 2 | E36: =-(+C36*D36) -> 0
A37: M16 | B37: =VLOOKUP(A37,'[1]PRODUCTO NACIONAL'!$A$4:$R$161,6,FALSE) -> D2003 Rollo Pike Deportivo 1.70m x 160gr | C37: =IFERROR(HLOOKUP(A37,[4]dimensiones_pdfs!$C$3:$Z$5,3,FALSE),0) -> 5.733715 | D37: =VLOOKUP(A37,'[1]PRODUCTO NACIONAL'!$A$4:$R$161,18,FALSE) -> 1.5306122 | E37: =-(+C37*D37) -> -8.7760945
A38: M59 | B38: =VLOOKUP(A38,'[1]PRODUCTO NACIONAL'!$A$4:$R$161,6,FALSE) -> PIKE LACOAST 20 PEI AZUL MARINO| OSCURO | C38: =IFERROR(HLOOKUP(A38,[4]dimensiones_pdfs!$C$3:$Z$5,3,FALSE),0) -> 0 | D38: =VLOOKUP(A38,'[1]PRODUCTO NACIONAL'!$A$4:$R$161,18,FALSE) -> 5.56184 | E38: =-(+C38*D38) -> 0
B43: GASTOS PERSONAL | C43: - | D43: - | E43: =+E66 -> -1108.856
B49: GASTOS PERSONAL
B50: DESCRIPCION | C50: PRECIO | D50: DÍAS | E50: VALOR
B51: CALANDRA | C51: 18 | D51: 6 | E51: =-(+C51*D51) -> -108
B52: LUZ | C52: 12.5 | D52: 6 | E52: =-(+C52*D52) -> -75
B53: PLAN DE CLARO NOVIEMBRE | C53: 15 | D53: 0 | E53: =-(+C53*D53) -> 0
B54: DOMESTICA | C54: =+'DIS. PRENDAS'!L12 -> 25.279583 | D54: 5 | E54: =-(+C54*D54) -> -126.39792
B55: PATTY GERENTE GENERAL | C55: ='DIS. PRENDAS'!R12 -> 36.48125 | D55: 6 | E55: =-(+C55*D55) -> -218.8875
B56: ASISTENTE Dunia GERENTE DE PRODUCCIÓN | C56: =+'DIS. PRENDAS'!O12 -> 31.502778 | D56: 6 | E56: =-(+C56*D56) -> -189.01667
B57: DISEÑADOR Luis | C57: ='DIS. PRENDAS'!L12 -> 25.279583 | D57: 6 | E57: =-(+C57*D57) -> -151.6775
B58: COSTURERO EDGAR | C58: =+'DIS. PRENDAS'!L12 -> 25.279583 | D58: 5.5 | E58: =-(+C58*D58) -> -139.03771
B59: COSTURERA Mami | C59: =+'DIS. PRENDAS'!L12 -> 25.279583 | D59: 3 | E59: =-(+C59*D59) -> -75.83875
B60: Costurera Elvia | C60: 20 | D60: 0 | E60: =-(+C60*D60) -> 0
B61: COSTURA EXTERNA | C61: 15 | D61: 0 | E61: =-(+C61*D61) -> 0
B62: CORTADOR-SUBLIMADOR EXTERNO Javier Espinoza | C62: =+'DIS. PRENDAS'!L12 -> 25.279583 | D62: 0 | E62: =-(+C62*D62) -> 0
B63: Corta Hilachas-Planchador-Empaqueta. ANGIE | C63: 20 | D63: 0 | E63: =-(+C63*D63) -> 0
B64: Empareja y Empaqueta Carla Dominguez | C64: 20 | D64: 0 | E64: =-(+C64*D64) -> 0
B65: CONTADORA Janinna Andrade NOVIEMBRE | C65: 25 | D65: 1 | E65: =-(+C65*D65) -> -25 | F65: declaracion de anexos de relación de dependencia
E66: =SUM(E51:E65) -> -1108.856
F69: EGRESA
B70: DESCRIPCION | C70: IMPRESIÓN | D70: INGRESA | F70: # POLINES | G70: BORDADO | H70: DTF/TPU | I70: GORRAS | J70: JARRO | K70: CUELLO BORDADOS | L70: PUÑO BORDADOS | M70: ENVIOS | N70: CINTA REFLECTIVA | O70: GASTOS VARIOS
C71: =SUM(C72:C300) -> 0 | D71: N° ORDEN | E71: =SUM(E72:E300) -> 720.92 | F71: =SUM(F72:F300) -> 25 | G71: =SUM(G72:G300) -> 0 | H71: =SUM(H72:H300) -> 0 | I71: =SUM(I72:I300) -> 0 | J71: =SUM(J72:J300) -> 0 | K71: =SUM(K72:K300) -> 4 | L71: =SUM(L72:L300) -> 4 | ... O71: =SUM(O72:O300) -> 13.5
B72: Mauricio Guerrero Impresión y 2 Kilos de Tela Pike | D72: SIN OT | E72: 49.72
B73: DON EDDY ITC | D73: SIN OT | E73: 38.6
B74: MOTORIZADO DON EDDY | D74: GASTOS | M74: 2
B75: PRENDAS SUBLIMADAS | D75: GASTOS | O75: 8
B76: MOTO FAST POLINES DE MACHALA | D76: GASTOS | M76: 3.5
B77: MOTORIZADO Y TINTA EPSON | D77: GASTOS | M77: 2 | O77: 5.5
B78: PRODUCCION | D78: 5429 | E78: 0 | F78: 20 DISEÑO ANULADA Javier Monserrate de Atletico Bolivar falta listado
B79: PRODUCCION | D79: 6070 | F79: Sacar en Optitex muestras de falda short
B80: PRODUCCION | D80: 6119 | E80: 0 | F80: Generar mockup de niños para la pagina yunpar
B81: PRODUCCION | D81: 6150 | F81: Molde Falda Short mitad plizado
B82: PRODUCCION | D82: 6183 | E82: 0 | F82: listo completar las tiras de ribb y colocar etiquetas que combines con polines y colores CMYK
B83: PRODUCCION | D83: 6264 | E83: 10 | K83: 2 | L83: 2
B84: PRODUCCION | D84: 6265 | E84: 24
B85: PRODUCCION | D85: 6266 | E85: 15 | F85: 1 | G85: HAPEVA DEBE
B86: PRODUCCION | D86: 6267 | E86: 22 | K86: 2 | L86: 2
B87: PRODUCCION | D87: 6268 | E87: 30
B88: PRODUCCION | D88: 6269 | E88: 187.5 | F88: 16
B89: PRODUCCION | D89: 6270 | E89: 72
B90: PRODUCCION | D90: 6271 | E90: 20 | F90: 1
B91: PRODUCCION | D91: 6272 | E91: 8
B92: PRODUCCION | D92: 6273 | E92: 64.1
B93: PRODUCCION | D93: 6274 | E93: 32 | F93: 2
B94: PRODUCCION | D94: 6275 | E94: 34 | F94: 2
B95: PRODUCCION | D95: 6276 | E95: 16 | F95: 1
B96: PRODUCCION | D96: 6277 | E96: 31 | F96: 2
B97: PRODUCCION | D97: 6278 | E97: 37
B98: PRODUCCION | D98: 6279 | F98: Falta orden
B99: PRODUCCION | D99: 6280 | F99: Falta orden
B100: PRODUCCION | D100: 6281 | E100: 30

Sheet 99
B2: SEMANA 99 CALANDRA
B3: Lunes 26 ENERO al sábado 31 de ENERO del 2026
B4: INGRESA | E4: =+E71 -> 0
B5: EGRESOS | F5: =SUM(E8:E47) -> -1002.805
B6: DIFERENCIA | E6: =+E4+F5 -> -1002.805 | H6: =+E6/E4 -> #DIV/0!
A7: ID | B7: EGRESOS | C7: CANTIDAD | D7: VALOR
A8: =IF('[1]PRODUCTO NACIONAL'!A14<>"",'[1]PRODUCTO NACIONAL'!A14,"") -> M11 | B8: =VLOOKUP(A8,'[1]PRODUCTO NACIONAL'!$A$4:$R$161,6,FALSE) -> IMPRESIÓN SIN DISEÑO, ANCHO 1.8X90gsm | C8: =IFERROR(HLOOKUP(A8,[4]dimensiones_pdfs!$C$3:$Z$5,3,FALSE),0) -> 59.833519 | D8: =VLOOKUP(A8,'[1]PRODUCTO NACIONAL'!$A$4:$R$161,18,FALSE) -> 1.3879841 | E8: =-(+C8*D8) -> -83.04797
A9: =IF('[1]PRODUCTO NACIONAL'!A18<>"",'[1]PRODUCTO NACIONAL'!A18,"") -> M15 | B9: =VLOOKUP(A9,'[1]PRODUCTO NACIONAL'!$A$4:$R$161,6,FALSE) -> D2006 Rollo Panal 1.70m x 160gr | C9: =IFERROR(HLOOKUP(A9,[4]dimensiones_pdfs!$C$3:$Z$5,3,FALSE),0) -> 11.213983 | D9: =VLOOKUP(A9,'[1]PRODUCTO NACIONAL'!$A$4:$R$161,18,FALSE) -> 1.6348774 | E9: =-(+C9*D9) -> -18.333488
A10: =IF('[1]PRODUCTO NACIONAL'!A27<>"",'[1]PRODUCTO NACIONAL'!A27,"") -> M24 | B10: =IF('[1]PRODUCTO NACIONAL'!F27<>"",'[1]PRODUCTO NACIONAL'!F27,"") -> POLIN GUTMAN T8-10 | T10-12 | C10: =F71 -> 0 | D10: =IF('[1]PRODUCTO NACIONAL'!R27<>"",'[1]PRODUCTO NACIONAL'!R27,"") -> 1.925065 | E10: =-(+C10*D10) -> 0
B11: =+G70 -> BORDADO | C11: =G71 -> 0 | D11: 1 | E11: =-(+C11*D11) -> 0
B12: =+H70 -> DTF/TPU | C12: =H71 -> 0 | D12: 1 | E12: =-(+C12*D12) -> 0
B13: =+I70 -> GORRAS | C13: =I71 -> 0 | D13: 2 | E13: =-(+C13*D13) -> 0
B14: =+J70 -> JARRO | C14: =J71 -> 0 | E14: =-(+C14*D14) -> 0
A15: =IF('[1]PRODUCTO NACIONAL'!A67<>"",'[1]PRODUCTO NACIONAL'!A67,"") -> M64 | B15: =IF('[1]PRODUCTO NACIONAL'!F67<>"",'[1]PRODUCTO NACIONAL'!F67,"") -> CUELLOS20 PEI|NEGRO AZABACHE Y MAS. | C15: =K71 -> 0 | D15: =VLOOKUP(A15,'[1]PRODUCTO NACIONAL'!$A$4:$R$161,18,FALSE) -> 0.47644606 | E15: =-(+C15*D15) -> 0
A16: =IF('[1]PRODUCTO NACIONAL'!A68<>"",'[1]PRODUCTO NACIONAL'!A68,"") -> M65 | B16: =IF('[1]PRODUCTO NACIONAL'!F68<>"",'[1]PRODUCTO NACIONAL'!F68,"") -> PUÑOS20 PEI|NEGRO AZABACHE Y MAS. | C16: =L71 -> 0 | D16: =VLOOKUP(A16,'[1]PRODUCTO NACIONAL'!$A$4:$R$161,18,FALSE) -> 0.23822303 | E16: =-(+C16*D16) -> 0
B17: =+M70 -> ENVIOS | C17: =M71 -> 0 | D17: 1 | E17: =-(+C17*D17) -> 0
A18: =IF('[1]PRODUCTO NACIONAL'!A76<>"",'[1]PRODUCTO NACIONAL'!A76,"") -> M73 | B18: =IF('[1]PRODUCTO NACIONAL'!F76<>"",'[1]PRODUCTO NACIONAL'!F76,"") -> CINTA REFLECTIVA DE 3cm de anchox1m | C18: =N71 -> 0 | D18: =VLOOKUP(A18,'[1]PRODUCTO NACIONAL'!$A$4:$R$161,18,FALSE) -> 1.3999945 | E18: =-(+C18*D18) -> 0
A19: =IF('[1]PRODUCTO NACIONAL'!A28<>"",'[1]PRODUCTO NACIONAL'!A28,"") -> M25 | B19: =VLOOKUP(A19,'[1]PRODUCTO NACIONAL'!$A$4:$R$161,6,FALSE) -> ALGODÓN ARUBA PEI AZUL MARINO| COLORES| BLANCO | C19: =IFERROR(HLOOKUP(A19,[4]dimensiones_pdfs!$C$3:$Z$5,3,FALSE),0) -> 0 | D19: =VLOOKUP(A19,'[1]PRODUCTO NACIONAL'!$A$4:$R$161,18,FALSE) -> 4.8341953 | E19: =-(+C19*D19) -> 0
A20: M61 | B20: =VLOOKUP(A20,'[1]PRODUCTO NACIONAL'!$A$4:$R$161,6,FALSE) -> INTERLOCK 40 SPUN 1.2 BLANCO FROZEN | C20: =IFERROR(HLOOKUP(A20,[4]dimensiones_pdfs!$C$3:$Z$5,3,FALSE),0) -> 0 | D20: =VLOOKUP(A20,'[1]PRODUCTO NACIONAL'!$A$4:$R$161,18,FALSE) -> 4.2071437 | E20: =-(+C20*D20) -> 0
A21: =IF('[1]PRODUCTO NACIONAL'!A61<>"",'[1]PRODUCTO NACIONAL'!A61,"") -> M58 | B21: =VLOOKUP(A21,'[1]PRODUCTO NACIONAL'!$A$4:$R$161,6,FALSE) -> PIKE LACOAST 20 PEI CELESTE| CLARO | C21: =IFERROR(HLOOKUP(A21,[4]dimensiones_pdfs!$C$3:$Z$5,3,FALSE),0) -> 0 | D21: =VLOOKUP(A21,'[1]PRODUCTO NACIONAL'!$A$4:$R$161,18,FALSE) -> 4.9712 | E21: =-(+C21*D21) -> 0
A22: =IF('[1]PRODUCTO NACIONAL'!A62<>"",'[1]PRODUCTO NACIONAL'!A62,"") -> M59 | B22: =VLOOKUP(A22,'[1]PRODUCTO NACIONAL'!$A$4:$R$161,6,FALSE) -> PIKE LACOAST 20 PEI AZUL MARINO| OSCURO | C22: =IFERROR(HLOOKUP(A22,[4]dimensiones_pdfs!$C$3:$Z$5,3,FALSE),0) -> 0 | D22: =VLOOKUP(A22,'[1]PRODUCTO NACIONAL'!$A$4:$R$161,18,FALSE) -> 5.56184 | E22: =-(+C22*D22) -> 0
A23: =IF('[1]PRODUCTO NACIONAL'!A21<>"",'[1]PRODUCTO NACIONAL'!A21,"") -> M18 | B23: =VLOOKUP(A23,'[1]PRODUCTO NACIONAL'!$A$4:$R$161,6,FALSE) -> RIBB 150TEX COLORES| POLIESTER | C23: =IFERROR(HLOOKUP(A23,[4]dimensiones_pdfs!$C$3:$Z$5,3,FALSE),0) -> 0.11478549 | D23: =VLOOKUP(A23,'[1]PRODUCTO NACIONAL'!$A$4:$R$161,18,FALSE) -> 2.1063822 | E23: =-(+C23*D23) -> -0.24178212
A24: =IF('[1]PRODUCTO NACIONAL'!A78<>"",'[1]PRODUCTO NACIONAL'!A78,"") -> M75 | B24: =VLOOKUP(A24,'[1]PRODUCTO NACIONAL'!$A$4:$R$161,6,FALSE) -> Ribb Lugano 100% POLIESTER | C24: =IFERROR(HLOOKUP(A24,[4]dimensiones_pdfs!$C$3:$Z$5,3,FALSE),0) -> 0 | D24: =VLOOKUP(A24,'[1]PRODUCTO NACIONAL'!$A$4:$R$161,18,FALSE) -> 4.5378 | E24: =-(+C24*D24) -> 0
A25: =IF('[1]PRODUCTO NACIONAL'!A30<>"",'[1]PRODUCTO NACIONAL'!A30,"") -> M27 | B25: =VLOOKUP(A25,'[1]PRODUCTO NACIONAL'!$A$4:$R$161,6,FALSE) -> VIOTO PESADA BLANCA|NEGRO|NARANJA FOSFORESCENTE | C25: =IFERROR(HLOOKUP(A25,[4]dimensiones_pdfs!$C$3:$Z$5,3,FALSE),0) -> 0 | D25: =VLOOKUP(A25,'[1]PRODUCTO NACIONAL'!$A$4:$R$161,18,FALSE) -> 1.9499895 | E25: =-(+C25*D25) -> 0
A26: =IF('[1]PRODUCTO NACIONAL'!A22<>"",'[1]PRODUCTO NACIONAL'!A22,"") -> M19 | B26: =VLOOKUP(A26,'[1]PRODUCTO NACIONAL'!$A$4:$R$161,6,FALSE) -> RIVER TEX NEGRO|COLORES | C26: =IFERROR(HLOOKUP(A26,[4]dimensiones_pdfs!$C$3:$Z$5,3,FALSE),0) -> 0 | D26: =VLOOKUP(A26,'[1]PRODUCTO NACIONAL'!$A$4:$R$161,18,FALSE) -> 2.4101474 | E26: =-(+C26*D26) -> 0
A27: =IF('[1]PRODUCTO NACIONAL'!A15<>"",'[1]PRODUCTO NACIONAL'!A15,"") -> M12 | B27: =VLOOKUP(A27,'[1]PRODUCTO NACIONAL'!$A$4:$R$161,6,FALSE) -> LINO JARUBA | C27: =IFERROR(HLOOKUP(A27,[4]dimensiones_pdfs!$C$3:$Z$5,3,FALSE),0) -> 0 | D27: =VLOOKUP(A27,'[1]PRODUCTO NACIONAL'!$A$4:$R$161,18,FALSE) -> 1.8905 | E27: =-(+C27*D27) -> 0
A28: =+'[1]PRODUCTO NACIONAL'!$A$4 -> M1 | B28: =VLOOKUP(A28,'[1]PRODUCTO NACIONAL'!$A$4:$R$161,6,FALSE) -> NYLON | C28: =IFERROR(HLOOKUP(A28,[4]dimensiones_pdfs!$C$3:$Z$5,3,FALSE),0) -> 0 | D28: =VLOOKUP(A28,'[1]PRODUCTO NACIONAL'!$A$4:$R$161,18,FALSE) -> 1.78999 | E28: =-(+C28*D28) -> 0
A29: M17 | B29: =VLOOKUP(A29,'[1]PRODUCTO NACIONAL'!$A$4:$R$161,6,FALSE) -> D2008 Rollo Jersy Spandex 1.80m x 275gr | C29: =IFERROR(HLOOKUP(A29,[4]dimensiones_pdfs!$C$3:$Z$5,3,FALSE),0) -> 0 | D29: =VLOOKUP(A29,'[1]PRODUCTO NACIONAL'!$A$4:$R$161,18,FALSE) -> 3.4782609 | E29: =-(+C29*D29) -> 0
A30: M35 | B30: =VLOOKUP(A30,'[1]PRODUCTO NACIONAL'!$A$4:$R$161,6,FALSE) -> NICO SPORT|BLANCO | C30: =IFERROR(HLOOKUP(A30,[4]dimensiones_pdfs!$C$3:$Z$5,3,FALSE),0) -> 0 | D30: =VLOOKUP(A30,'[1]PRODUCTO NACIONAL'!$A$4:$R$161,18,FALSE) -> 2.316 | E30: =-(+C30*D30) -> 0
A31: M37 | B31: =VLOOKUP(A31,'[1]PRODUCTO NACIONAL'!$A$4:$R$161,6,FALSE) -> MURRAY|BLANCA | C31: =IFERROR(HLOOKUP(A31,[4]dimensiones_pdfs!$C$3:$Z$5,3,FALSE),0) -> 0 | D31: =VLOOKUP(A31,'[1]PRODUCTO NACIONAL'!$A$4:$R$161,18,FALSE) -> 2.2825013 | E31: =-(+C31*D31) -> 0
A32: M36 | B32: =VLOOKUP(A32,'[1]PRODUCTO NACIONAL'!$A$4:$R$161,6,FALSE) -> Rollo de Galeon 150 ancho | C32: =IFERROR(HLOOKUP(A32,[4]dimensiones_pdfs!$C$3:$Z$5,3,FALSE),0) -> 7.3363607 | D32: =VLOOKUP(A32,'[1]PRODUCTO NACIONAL'!$A$4:$R$161,18,FALSE) -> 0.775 | E32: =-(+C32*D32) -> -5.6856795
A33: M78 | B33: =VLOOKUP(A33,'[1]PRODUCTO NACIONAL'!$A$4:$R$161,6,FALSE) -> PIEL DE DURAZNO | C33: =IFERROR(HLOOKUP(A33,[4]dimensiones_pdfs!$C$3:$Z$5,3,FALSE),0) -> 0 | D33: =VLOOKUP(A33,'[1]PRODUCTO NACIONAL'!$A$4:$R$161,18,FALSE) -> 2.5 | E33: =-(+C33*D33) -> 0
A34: M14 | B34: =VLOOKUP(A34,'[1]PRODUCTO NACIONAL'!$A$4:$R$161,6,FALSE) -> D2002 Rollo Ernest 1.70m x 140gr | C34: =IFERROR(HLOOKUP(A34,[4]dimensiones_pdfs!$C$3:$Z$5,3,FALSE),0) -> 12.418262 | D34: =VLOOKUP(A34,'[1]PRODUCTO NACIONAL'!$A$4:$R$161,18,FALSE) -> 1.4285714 | E34: =-(+C34*D34) -> -17.740374
A35: M28 | B35: =VLOOKUP(A35,'[1]PRODUCTO NACIONAL'!$A$4:$R$161,6,FALSE) -> PRADA LISA | C35: =IFERROR(HLOOKUP(A35,[4]dimensiones_pdfs!$C$3:$Z$5,3,FALSE),0) -> 0 | D35: =VLOOKUP(A35,'[1]PRODUCTO NACIONAL'!$A$4:$R$161,18,FALSE) -> 2.52024 | E35: =-(+C35*D35) -> 0
A36: M34 | B36: =VLOOKUP(A36,'[1]PRODUCTO NACIONAL'!$A$4:$R$161,6,FALSE) -> PRADA ROMBOS|CUADROS | C36: =IFERROR(HLOOKUP(A36,[4]dimensiones_pdfs!$C$3:$Z$5,3,FALSE),0) -> 0 | D36: 2 | E36: =-(+C36*D36) -> 0
A37: M16 | B37: =VLOOKUP(A37,'[1]PRODUCTO NACIONAL'!$A$4:$R$161,6,FALSE) -> D2003 Rollo Pike Deportivo 1.70m x 160gr | C37: =IFERROR(HLOOKUP(A37,[4]dimensiones_pdfs!$C$3:$Z$5,3,FALSE),0) -> 5.733715 | D37: =VLOOKUP(A37,'[1]PRODUCTO NACIONAL'!$A$4:$R$161,18,FALSE) -> 1.5306122 | E37: =-(+C37*D37) -> -8.7760945
A38: M59 | B38: =VLOOKUP(A38,'[1]PRODUCTO NACIONAL'!$A$4:$R$161,6,FALSE) -> PIKE LACOAST 20 PEI AZUL MARINO| OSCURO | C38: =IFERROR(HLOOKUP(A38,[4]dimensiones_pdfs!$C$3:$Z$5,3,FALSE),0) -> 0 | D38: =VLOOKUP(A38,'[1]PRODUCTO NACIONAL'!$A$4:$R$161,18,FALSE) -> 5.56184 | E38: =-(+C38*D38) -> 0
B43: GASTOS PERSONAL | C43: - | D43: - | E43: =+E66 -> -868.97958
B49: GASTOS PERSONAL
B50: DESCRIPCION | C50: PRECIO | D50: DÍAS | E50: VALOR
B51: CALANDRA | C51: 18 | D51: 6 | E51: =-(+C51*D51) -> -108
B52: LUZ | C52: 12.5 | D52: 6 | E52: =-(+C52*D52) -> -75
B53: PLAN DE CLARO NOVIEMBRE | C53: 15 | D53: 0 | E53: =-(+C53*D53) -> 0
B54: DOMESTICA | C54: =+'DIS. PRENDAS'!L12 -> 25.279583 | D54: 5 | E54: =-(+C54*D54) -> -126.39792
B55: PATTY GERENTE GENERAL | C55: ='DIS. PRENDAS'!R12 -> 36.48125 | D55: 6 | E55: =-(+C55*D55) -> -218.8875
B56: ASISTENTE Dunia GERENTE DE PRODUCCIÓN | C56: =+'DIS. PRENDAS'!O12 -> 31.502778 | D56: 6 | E56: =-(+C56*D56) -> -189.01667
B57: DISEÑADOR Luis | C57: ='DIS. PRENDAS'!L12 -> 25.279583 | D57: 6 | E57: =-(+C57*D57) -> -151.6775
B58: COSTURERO EDGAR | C58: =+'DIS. PRENDAS'!L12 -> 25.279583 | D58: 0 | E58: =-(+C58*D58) -> 0
B59: COSTURERA Mami | C59: =+'DIS. PRENDAS'!L12 -> 25.279583 | D59: 0 | E59: =-(+C59*D59) -> 0
B60: Costurera Elvia | C60: 20 | D60: 0 | E60: =-(+C60*D60) -> 0
B61: COSTURA EXTERNA | C61: 15 | D61: 0 | E61: =-(+C61*D61) -> 0
B62: CORTADOR-SUBLIMADOR EXTERNO Javier Espinoza | C62: =+'DIS. PRENDAS'!L12 -> 25.279583 | D62: 0 | E62: =-(+C62*D62) -> 0
B63: Corta Hilachas-Planchador-Empaqueta. ANGIE | C63: 20 | D63: 0 | E63: =-(+C63*D63) -> 0
B64: Empareja y Empaqueta Carla Dominguez | C64: 20 | D64: 0 | E64: =-(+C64*D64) -> 0
B65: CONTADORA Janinna Andrade NOVIEMBRE | C65: 25 | D65: 0 | E65: =-(+C65*D65) -> 0
E66: =SUM(E51:E65) -> -868.97958
F69: EGRESA
B70: DESCRIPCION | C70: IMPRESIÓN | D70: INGRESA | F70: # POLINES | G70: BORDADO | H70: DTF/TPU | I70: GORRAS | J70: JARRO | K70: CUELLO BORDADOS | L70: PUÑO BORDADOS | M70: ENVIOS | N70: CINTA REFLECTIVA | O70: GASTOS VARIOS
C71: =SUM(C72:C284) -> 0 | D71: N° ORDEN | E71: =SUM(E72:E284) -> 0 | F71: =SUM(F72:F284) -> 0 | G71: =SUM(G72:G284) -> 0 | H71: =SUM(H72:H284) -> 0 | I71: =SUM(I72:I284) -> 0 | J71: =SUM(J72:J284) -> 0 | K71: =SUM(K72:K284) -> 0 | L71: =SUM(L72:L284) -> 0 | ... O71: =SUM(O72:O284) -> 0
B78: PRODUCCION | D78: 5429 | E78: 0 | F78: 20 DISEÑO ANULADA Javier Monserrate de Atletico Bolivar falta listado
B79: PRODUCCION | D79: 6070 | F79: Sacar en Optitex muestras de falda short
B80: PRODUCCION | D80: 6119 | E80: 0 | F80: Generar mockup de niños para la pagina yunpar
B81: PRODUCCION | D81: 6150 | F81: Molde Falda Short mitad plizado
B82: PRODUCCION | D82: 6266 | E82: 0 | F82: HAPEVA DEBE
B83: PRODUCCION | D83: 6279 | F83: Falta orden
B84: PRODUCCION | D84: 6280 | F84: Falta orden
B85: PRODUCCION | D85: 6282
B86: PRODUCCION | D86: 6283
B87: PRODUCCION | D87: 6284
B88: PRODUCCION | D88: 6285
B89: PRODUCCION | D89: 6286
B90: PRODUCCION | D90: 6287
B91: PRODUCCION | D91: 6288
B92: PRODUCCION | D92: 6289
B93: PRODUCCION | D93: 6290
B94: PRODUCCION | D94: 6291
B95: PRODUCCION | D95: 6292
B96: PRODUCCION | D96: 6293
... B103: PRODUCCION | D103: 6300

Sheet MENSUAL
F1: =+SUM(F3:F6) -> 4827.83 | G1: =+SUM(G3:G6) -> -5955.5963 | J1: =+F1+G1 -> -1127.7663
E2: FECHAS | F2: INGRESOS | G2: EGRESOS | H2: SALDO | I2: VALOR X MES | J2: CAJA
A3: ENERO | B3: 96 | C3: ='96'!B2 -> SEMANA 96 CALANDRA | D3: =+'96'!B3 -> Lunes 5 ENERO al sábado 10 de ENERO del 2026 | E3: 45936 | F3: ='96'!E4 -> 444.5 | G3: ='96'!F5 -> -1140.0859 | H3: ='96'!E6 -> -695.58585 | I3: =SUM(H3:H6) -> -1127.7663 | J3: =SUM(H3:H254) -> -1127.7663
B4: 97 | C4: ='97'!B2 -> SEMANA 97 CALANDRA | D4: =+'97'!B3 -> Lunes 12 ENERO al sábado 17 de ENERO del 2026 | E4: 45936 | F4: ='97'!E4 -> 3662.41 | G4: ='97'!F5 -> -2511.5387 | H4: ='97'!E6 -> 1150.8713
B5: 98 | C5: ='98'!B2 -> SEMANA 98 CALANDRA | D5: =+'98'!B3 -> Lunes 19 ENERO al sábado 24 de ENERO del 2026 | E5: 45936 | F5: ='98'!E4 -> 720.92 | G5: ='98'!F5 -> -1301.1667 | H5: ='98'!E6 -> -580.24673
B6: 99 | C6: ='99'!B2 -> SEMANA 99 CALANDRA | D6: =+'99'!B3 -> Lunes 26 ENERO al sábado 31 de ENERO del 2026 | E6: 45936 | F6: ='99'!E4 -> 0 | G6: ='99'!F5 -> -1002.805 | H6: ='99'!E6 -> -1002.805

Sheet TELAS
A1: TELAS E IMPRESIONES
E2: FECHAS | F2: INGRESOS | G2: VALOR X MES | H2: CAJA
A3: ENERO | B3: 96 | C3: ='96'!B2 -> SEMANA 96 CALANDRA | D3: =+'96'!B3 -> Lunes 5 ENERO al sábado 10 de ENERO del 2026 | E3: 45936 | F3: =SUM('96'!C9,'96'!C34,'96'!C37,'96'!C8) -> 76.759921 | G3: =SUM(F3:F6) -> 778.22045 | H3: =SUM(F3:F254) -> 778.22045
B4: 97 | C4: ='97'!B2 -> SEMANA 97 CALANDRA | D4: =+'97'!B3 -> Lunes 12 ENERO al sábado 17 de ENERO del 2026 | E4: 45936 | F4: =SUM('97'!C9,'97'!C34,'97'!C37,'97'!C8) -> 523.06158
B5: 98 | C5: ='98'!B2 -> SEMANA 98 CALANDRA | D5: =+'98'!B3 -> Lunes 19 ENERO al sábado 24 de ENERO del 2026 | E5: 45936 | F5: =SUM('98'!C9,'98'!C34,'98'!C37,'98'!C8) -> 89.199479
B6: 99 | C6: ='99'!B2 -> SEMANA 99 CALANDRA | D6: =+'99'!B3 -> Lunes 26 ENERO al sábado 31 de ENERO del 2026 | E6: 45936 | F6: =SUM('99'!C9,'99'!C34,'99'!C37,'99'!C8) -> 89.199479

Sheet DIS. PRENDAS
B1: DISEÑOS GENERADOS DURANTE CADA MES | H1: PROMEDIO PRENDAS | I1: =+AVERAGE(C3:C20) -> 707 | K1: DIS./VENDEDORA/COSTURERA | N1: G. PRODUCCIÓN | Q1: GERENTE GENERAL
B2: MES/2026 | C2: PRENDAS | D2: DTF | E2: POLINES | F2: TOTAL | H2: SUELDO DISEÑADOR | I2: =+L11 -> 606.71 | K2: SUELDO BASICO | L2: 475 | N2: SUELDO BASICO | O2: 600 | Q2: SUELDO BASICO | R2: 700
B3: ENERO | C3: 707 | D3: 5 | E3: 54 | F3: =SUM(C3:E3) -> 766 | H3: COSTO PRENDA | I3: =+I2/I1 -> 0.8581471 | K3: % IESS PATRONAL 11.15% | L3: =ROUND(L2*11.15%,2) -> 52.96 | N3: % IESS PATRONAL 11.15% | O3: =ROUND(O2*11.15%,2) -> 66.9 | Q3: % IESS PATRONAL 11.15% | R3: =ROUND(R2*11.15%,2) -> 78.05
B4: FEBRERO | K4: SUELDO MENSUAL | L4: =+L2+L3 -> 527.96 | N4: SUELDO MENSUAL | O4: =+O2+O3 -> 666.9 | Q4: SUELDO MENSUAL | R4: =+R2+R3 -> 778.05
B5: MARZO | H5: PROMEDIO PRENDAS | I5: =+I1 -> 707
B6: ABRIL | H6: SUELDO VENDEDORA | I6: =+L11 -> 606.71 | K6: SUELDO ANUAL | L6: =+L4*12 -> 6335.52 | N6: SUELDO ANUAL | O6: =+O4*12 -> 8002.8 | Q6: SUELDO ANUAL | R6: =+R4*12 -> 9336.6
B7: MAYO | H7: COSTO PRENDA | I7: =+I6/I5 -> 0.8581471 | K7: DECIMO TERCERO FIN AÑOS | L7: =+L2 -> 475 | N7: DECIMO TERCERO FIN AÑOS | O7: =+O2 -> 600 | Q7: DECIMO TERCERO FIN AÑOS | R7: =+R2 -> 700
B8: JUNIO | K8: DECIMO CUARTO MARZO | L8: 470 | N8: DECIMO CUARTO MARZO | O8: 470 | Q8: DECIMO CUARTO MARZO | R8: 470
B9: JULIO | H9: PROMEDIO PRENDAS | I9: =+I5 -> 707
B10: AGOSTO | H10: SUELDO COSTURERA | I10: =+L11 -> 606.71 | K10: SUELDOS TOTALES | L10: =+L6+L7+L8 -> 7280.52 | N10: SUELDOS TOTALES | O10: =+O6+O7+O8 -> 9072.8 | Q10: SUELDOS TOTALES | R10: =+R6+R7+R8 -> 10506.6
B11: SEPTIEMBRE | H11: COSTO PRENDA | I11: =+I10/I9 -> 0.8581471 | K11: MENSUALIZADO | L11: =+L10/12 -> 606.71 | N11: MENSUALIZADO | O11: =+O10/12 -> 756.06667 | Q11: MENSUALIZADO | R11: =+R10/12 -> 875.55
B12: OCTUBRE | K12: DIARIO | L12: =+L11/24 -> 25.279583 | N12: DIARIO | O12: =+O11/24 -> 31.502778 | Q12: DIARIO | R12: =+R11/24 -> 36.48125
B13: NOVIEMBRE | H13: PROMEDIO PRENDAS | I13: =+I5 -> 707
B14: DICIEMBRE | H14: SUELDO G. PRODUCCIÓN | I14: =+O11 -> 756.06667 | K14: % IESS AFILIADO 9.45% | L14: =+L2*9.45% -> 44.8875 | N14: % IESS AFILIADO 9.45 | O14: =+O2*9.45% -> 56.7 | Q14: % IESS AFILIADO 9.45 | R14: =+R2*9.45% -> 66.15
H15: COSTO PRENDA | I15: =+I14/I13 -> 1.0694012 | K15: NETO MENSUAL | L15: =+L11-L14 -> 561.8225 | N15: NETO MENSUAL | O15: =+O11-O14 -> 699.36667 | Q15: NETO MENSUAL | R15: =+R11-R14 -> 809.4
K16: COSTO HORARIO IESS | L16: =+L11/(8*24) -> 3.1599479 | N16: COSTO HORARIO IESS | O16: =+O11/(8*24) -> 3.9378472 | Q16: COSTO HORARIO IESS | R16: =+R11/(8*24) -> 4.5601562
H17: PROMEDIO PRENDAS | I17: =+I9 -> 707 | K17: COSTO HORARIO EVENTUAL | L17: =+L2/(8*24) -> 2.4739583
H18: SUELDO GERENTE GENERAL | I18: =+R11 -> 875.55
H19: COSTO PRENDA | I19: =+I18/I17 -> 1.2384017
L20: =+L2-L14 -> 430.1125
H21: COSTO FIJO POR PRENDA | I21: =ROUND(+I19+I15+I11+I7+I3,2) -> 4.88
L23: =+L7/12 -> 39.583333
L24: =+L23*4 -> 158.33333

Sheet DESPERDICIO
B1: =+STDEVA(B3:B16) -> 0.062595219 | D1: 1 | I1: =+D1+1 -> 2 | N1: =+I1+1 -> 3 | S1: =+N1+1 -> 4 | X1: =+S1+1 -> 5 | AC1: =+X1+1 -> 6 | AH1: =+AC1+1 -> 7
B2: DESPERDICIOS | D2: =+SUM(D4:D19) -> 76.39 | F2: PESO TELA KG | G2: 24.52 | I2: =+SUM(I4:I19) -> 84.03 | K2: PESO TELA KG | L2: 24.56 | N2: =+SUM(N4:N19) -> 86.95 | P2: PESO TELA KG | Q2: 24.48 | S2: =+SUM(S4:S19) -> 86.02 | U2: PESO TELA KG | V2: 23.86 | X2: =+SUM(X4:X19) -> 88.4 | Z2: PESO TELA KG | AA2: 24.5 | AC2: =+SUM(AC4:AC19) -> 95.55 | AE2: PESO TELA KG | AF2: 26 | AH2: =+SUM(AH4:AH19) -> 90.97 | AJ2: PESO TELA KG | AK2: 25.9
A3: C1 | B3: =+G8 -> 0.2197408 | D3: LONG IMPRESIÓN | F3: RENDIMIENTO | G3: 3.8 | I3: LONG IMPRESIÓN | K3: RENDIMIENTO | L3: 3.8 | N3: LONG IMPRESIÓN | P3: RENDIMIENTO | Q3: 3.8 | S3: LONG IMPRESIÓN | U3: RENDIMIENTO | V3: 3.8 | X3: LONG IMPRESIÓN | Z3: RENDIMIENTO | AA3: 3.8 | AC3: LONG IMPRESIÓN | AE3: RENDIMIENTO | AF3: 3.8 | AH3: LONG IMPRESIÓN | AJ3: RENDIMIENTO | AK3: 3.8
A4: C2 | B4: =+L8 -> 0.11065096 | D4: 16.94 | I4: 45.45 | N4: 88.76 | S4: 21.84 | X4: 46.3 | AC4: 32.05 | AH4: 90.97
A5: C3 | B5: =+Q8 -> 0.069856239 | D5: 34.1 | F5: LONG TELA | G5: =+G2*G3 -> 93.176 | I5: 11.37 | K5: LONG TELA | L5: =+L2*L3 -> 93.328 | N5: -1.81 | P5: LONG TELA | Q5: =+Q2*Q3 -> 93.024 | S5: 1.75 | U5: LONG TELA | V5: =+V2*V3 -> 90.668 | X5: 13.8 | Z5: LONG TELA | AA5: =+AA2*AA3 -> 93.1 | AC5: 31 | AE5: LONG TELA | AF5: =+AF2*AF3 -> 98.8 | AJ5: LONG TELA | AK5: =+AK2*AK3 -> 98.42
A6: C4 | B6: =+V8 -> 0.054033946 | D6: 21.33 | I6: 27.03 | S6: 59.71 | X6: 9.21 | AC6: 2.5
A7: C5 | B7: =+AA8 -> 0.053167421 | D7: -0.83 | F7: LOG DESPERD | G7: =+G5-D2 -> 16.786 | I7: 5.12 | K7: LOG DESPERD | L7: =+L5-I2 -> 9.298 | P7: LOG DESPERD | Q7: =+Q5-N2 -> 6.074 | S7: 2.72 | U7: LOG DESPERD | V7: =+V5-S2 -> 4.648 | X7: 25.41 | Z7: LOG DESPERD | AA7: =+AA5-X2 -> 4.7 | AC7: 13 | AE7: LOG DESPERD | AF7: =+AF5-AC2 -> 3.25 | AJ7: LOG DESPERD | AK7: =+AK5-AH2 -> 7.45
A8: C6 | B8: =+AF8 -> 0.034013605 | D8: -0.65 | F8: % DESPERDICIO | G8: =IFERROR(+G7/D2,"") -> 0.2197408 | I8: -0.43 | K8: % DESPERDICIO | L8: =IFERROR(+L7/I2,"") -> 0.11065096 | P8: % DESPERDICIO | Q8: =IFERROR(+Q7/N2,"") -> 0.069856239 | U8: % DESPERDICIO | V8: =IFERROR(+V7/S2,"") -> 0.054033946 | X8: -1.6 | Z8: % DESPERDICIO | AA8: =IFERROR(+AA7/X2,"") -> 0.053167421 | AC8: 17 | AE8: % DESPERDICIO | AF8: =IFERROR(+AF7/AC2,"") -> 0.034013605 | AJ8: % DESPERDICIO | AK8: =IFERROR(+AK7/AH2,"") -> 0.08189513
A9: C7 | B9: =+AK8 -> 0.08189513 | D9: -0.82 | I9: -1.44 | X9: -4.72
D10: 1.6 | I10: -0.26
D11: 4.72 | I11: -1.84
I12: -0.64
I13: -0.33

Sheet IMPRE. m
A1: CANTIDAD DE IMPRESIÓN POR METROS AL DIA
A2: DIA | B2: ANCHO 1,62 | C2: AREA | D2: ANCHO 1,80 | E2: AREA | F2: LONGITUD TOTAL
A3: LUNES 19/08/2024 | B3: 56.09 | C3: =+B3*1.6 -> 89.744 | D3: 49.09 | E3: =+D3*1.7 -> 83.453 | F3: =+B3+D3 -> 105.18 | H3: =20/100 -> 0.2 | L3: =1.8*100 -> 180
A4: MARTES 20/08/2024 | B4: 45.39 | C4: =+B4*1.6 -> 72.624 | D4: 72.54 | E4: =+D4*1.7 -> 123.318 | F4: =+B4+D4 -> 117.93 | L4: 20
A5: MIERCOLES 21/08/2024 | B5: 0 | C5: =+B5*1.6 -> 0 | D5: 60 | E5: =+D5*1.7 -> 102 | F5: =+B5+D5 -> 60 | J5: =SUM(C3:C7) -> 269.888
A6: JUEVES 22/08/2024 | B6: 9.38 | C6: =+B6*1.6 -> 15.008 | D6: 55.89 | E6: =+D6*1.7 -> 95.013 | F6: =+B6+D6 -> 65.27 | H6: =5*20 -> 100 | J6: =SUM(E3:E7) -> 485.299 | L6: =+L4/L3 -> 0.11111111
A7: VIERNES 23/08/2024 | B7: 57.82 | C7: =+B7*1.6 -> 92.512 | D7: 47.95 | E7: =+D7*1.7 -> 81.515 | F7: =+B7+D7 -> 105.77 | H7: =SUM(F3:F7) -> 454.15 | J7: =SUM(J5:J6) -> 755.187
A8: LUNES 2/SEPTIEMBRE/2024 | B8: 72.22 | C8: =+B8*1.6 -> 115.552 | D8: 12.16 | E8: =+D8*1.7 -> 20.672 | F8: =+B8+D8 -> 84.38 | J8: =+H6/J7 -> 0.13241753
A9: MARTES 3 SEPTIEMBRE/2024 | B9: 93.8 | C9: =+B9*1.6 -> 150.08 | D9: 37.34 | E9: =+D9*1.8 -> 67.212 | F9: =+B9+D9 -> 131.14
A10: MIERCOLES 4 SEPTIEMBRE/2024 | B10: 34.35 | C10: =+B10*1.6 -> 54.96 | D10: 9.7 | E10: =+D10*1.8 -> 17.46 | F10: =+B10+D10 -> 44.05
A11: JUEVES 5 SEPTIEMBRE/2024 | B11: 2.35 | C11: =+B11*1.6 -> 3.76 | D11: 68.85 | E11: =+D11*1.8 -> 123.93 | F11: =+B11+D11 -> 71.2
A12: VIERNES 6 SEPTIEMBRE/2024 | C12: =+B12*1.6 -> 0 | D12: 107.35 | E12: =+D12*1.8 -> 193.23 | F12: =+B12+D12 -> 107.35
A13: lunes, 9 de Septiembre/2024
A14: Martes, 10 de Septiembre/2024
A15: Miercoles, 11 de Septiembre/2024
A16: Jueves, 12 de Septiembre/2024
A17: Viernes, 13 de Septiembre/2024
A18: Sábado, 14 de Septiembre/2024
